[
  {
    "text": "[संगीत]",
    "start_time": 0.37,
    "duration": 18.669
  },
  {
    "text": "अनेकांच्या प्रमाणे मलाही वाटलं होतं की",
    "start_time": 16.88,
    "duration": 4.239
  },
  {
    "text": "कालच्या ज्ञानेश्वरीची आज भौतिक सुट्टी",
    "start_time": 19.039,
    "duration": 5.08
  },
  {
    "text": "आहे",
    "start_time": 21.119,
    "duration": 3.0
  },
  {
    "text": "तशा सरकारी सुविधा भगवंताच्या सेवेमध्ये",
    "start_time": 26.48,
    "duration": 9.48
  },
  {
    "text": "काय करणार",
    "start_time": 32.719,
    "duration": 3.241
  },
  {
    "text": "गोळा गेली आहेत का होईना आला वरती",
    "start_time": 40.239,
    "duration": 7.84
  },
  {
    "text": "आपला जप चांगला झाला असेल अशी आशा करतो.",
    "start_time": 44.399,
    "duration": 6.561
  },
  {
    "text": "भरून काढायचंच आहे बऱ्याच लोकांना त्याची",
    "start_time": 48.079,
    "duration": 5.841
  },
  {
    "text": "काल आठवण करणार होतो आज आपल्याला करतो आता",
    "start_time": 50.96,
    "duration": 6.0
  },
  {
    "text": "तीन चार महिनेच राहिलेत. आपल्यासमोर आपले",
    "start_time": 53.92,
    "duration": 5.6
  },
  {
    "text": "उद्दिष्ट असतीलच.",
    "start_time": 56.96,
    "duration": 5.599
  },
  {
    "text": "दोन तृतींश पेक्षा अधिक काळ आला गेलाय",
    "start_time": 59.52,
    "duration": 5.44
  },
  {
    "text": "त्यामुळे तीन चतुर्थांश पेक्षा अधिक काळ",
    "start_time": 62.559,
    "duration": 4.161
  },
  {
    "text": "गेला म्हणा",
    "start_time": 64.96,
    "duration": 6.4
  },
  {
    "text": "तर त्याच स्मरण करतो आणि फक्त स्वामींचे",
    "start_time": 66.72,
    "duration": 9.2
  },
  {
    "text": "स्मरण करून थांबतो",
    "start_time": 71.36,
    "duration": 8.32
  },
  {
    "text": "तेव्हा जी",
    "start_time": 75.92,
    "duration": 7.199
  },
  {
    "text": "अव्ययक्त संत मंडळी ज्यांचा शेवटी इथे",
    "start_time": 79.68,
    "duration": 6.0
  },
  {
    "text": "उल्लेख केलेला आहे",
    "start_time": 83.119,
    "duration": 6.961
  },
  {
    "text": "काल आपण संतांना मला म्हटली त्यात",
    "start_time": 85.68,
    "duration": 4.4
  },
  {
    "text": "इथलं प्रेम धरून इथं वास करीत असतात",
    "start_time": 90.96,
    "duration": 10.56
  },
  {
    "text": "त्यामध्ये स्वामी महाराज आहेत",
    "start_time": 97.2,
    "duration": 6.64
  },
  {
    "text": "अनेकांना अनेकांच्याकडे त्यांची उपासना",
    "start_time": 101.52,
    "duration": 6.84
  },
  {
    "text": "आहे अनेकांना त्यांचे नाम आहे",
    "start_time": 103.84,
    "duration": 4.52
  },
  {
    "text": "तर",
    "start_time": 109.36,
    "duration": 4.32
  },
  {
    "text": "आज त्यांची जयंती आहे",
    "start_time": 110.96,
    "duration": 5.68
  },
  {
    "text": "शुद्धीची",
    "start_time": 113.68,
    "duration": 5.01
  },
  {
    "text": "शनिवार",
    "start_time": 116.64,
    "duration": 5.099
  },
  {
    "text": "[संगीत]",
    "start_time": 118.69,
    "duration": 3.049
  },
  {
    "text": "करण शक्य नाही",
    "start_time": 127.439,
    "duration": 4.88
  },
  {
    "text": "तिथीचा निकाल हा एक विषय स्वतंत्र आहे",
    "start_time": 129.84,
    "duration": 5.28
  },
  {
    "text": "त्याच्यात आपण न पडलेल वर्ग कारण आपलं मूळ",
    "start_time": 132.319,
    "duration": 6.0
  },
  {
    "text": "काम हे",
    "start_time": 135.12,
    "duration": 5.839
  },
  {
    "text": "स्मरण करण्याचा आहे कुठल्या काय",
    "start_time": 138.319,
    "duration": 8.28
  },
  {
    "text": "निमित्ताने निमित्ताने असो आपण",
    "start_time": 140.959,
    "duration": 5.64
  },
  {
    "text": "भक्त चरित्रातही प्रशंमती जसं ज्ञानेश्वरी",
    "start_time": 148.0,
    "duration": 5.599
  },
  {
    "text": "दत्ता आहोत तिथे वाचलं असेल आपल्या लक्षात",
    "start_time": 150.72,
    "duration": 7.44
  },
  {
    "text": "असेल तेव्हा जे संत चरित्रातही प्रशंमशिती",
    "start_time": 153.599,
    "duration": 8.561
  },
  {
    "text": "त तिथे भगवंताचा जीव घोटाळतो",
    "start_time": 158.16,
    "duration": 8.159
  },
  {
    "text": "असं त्यांनी म्हटलेल आहे तेव्हा आजची तिथी",
    "start_time": 162.16,
    "duration": 7.6
  },
  {
    "text": "आहे ज्यांना त्यांनी माझा बाळ आहे असं",
    "start_time": 166.319,
    "duration": 6.161
  },
  {
    "text": "म्हटलं सुद्धा आहे अस म्हटलेल आहे स्वामी",
    "start_time": 169.76,
    "duration": 4.64
  },
  {
    "text": "सतत महाराज",
    "start_time": 172.48,
    "duration": 6.36
  },
  {
    "text": "आपल्याला त्यांची कल्पना असेल",
    "start_time": 174.4,
    "duration": 4.44
  },
  {
    "text": "त्यांचं मत ग्राह्य धरून ही",
    "start_time": 179.2,
    "duration": 7.119
  },
  {
    "text": "जयंती केली जाते",
    "start_time": 183.12,
    "duration": 5.36
  },
  {
    "text": "तेव्हा मूळ प्रश्न स्मरणाचाच असल्यामुळे",
    "start_time": 186.319,
    "duration": 5.441
  },
  {
    "text": "तो या निमित्ताने करून",
    "start_time": 188.48,
    "duration": 5.039
  },
  {
    "text": "काय असते याची पार्श्वभूमी आपल्याला फक्त",
    "start_time": 191.76,
    "duration": 5.28
  },
  {
    "text": "सांगून ठेवतो. की वृत्ती बदलणं आणि",
    "start_time": 193.519,
    "duration": 7.201
  },
  {
    "text": "माणसाचा देह कसा होईल हे पाहणं",
    "start_time": 197.04,
    "duration": 6.559
  },
  {
    "text": "यासाठी सगळ्या व्यवस्था आपल्या परीने",
    "start_time": 200.72,
    "duration": 5.36
  },
  {
    "text": "कार्यरत आहेत.",
    "start_time": 203.599,
    "duration": 4.64
  },
  {
    "text": "आपल्याकडून त्याला प्रतिसाद किती मिळतो",
    "start_time": 206.08,
    "duration": 5.6
  },
  {
    "text": "यावर आपल्याला त्याचा अनुभव येतो आणि",
    "start_time": 208.239,
    "duration": 5.681
  },
  {
    "text": "प्रगती पण होते.",
    "start_time": 211.68,
    "duration": 6.8
  },
  {
    "text": "आपला प्रतिसाद किती आहे? आता त्यात",
    "start_time": 213.92,
    "duration": 8.08
  },
  {
    "text": "जसे आपले प्रकार आहेत तसे त्या ज्या",
    "start_time": 218.48,
    "duration": 6.96
  },
  {
    "text": "व्यवस्था आहेत. त्यांचे आपल्याशी संपर्क",
    "start_time": 222.0,
    "duration": 5.68
  },
  {
    "text": "ठेवण्याचे प्रकार आहेत. त्यांचे उद्धार",
    "start_time": 225.44,
    "duration": 5.12
  },
  {
    "text": "करण्याचे प्रकार आहेत.",
    "start_time": 227.68,
    "duration": 7.919
  },
  {
    "text": "मुळात वृत्ती अभ्यासाने बदलायची गोष्ट खरी",
    "start_time": 230.56,
    "duration": 7.679
  },
  {
    "text": "सदवृत्ती किंवा सद्बुद्धी",
    "start_time": 235.599,
    "duration": 7.2
  },
  {
    "text": "ही मुळात दुर्लभ आहे अतिशय कठीण आहे",
    "start_time": 238.239,
    "duration": 8.241
  },
  {
    "text": "जसं पाणी उभा खाली जावं हे सोप आहे आणि",
    "start_time": 242.799,
    "duration": 7.281
  },
  {
    "text": "चढवण जस कठीण आहे वरती शिखरावर",
    "start_time": 246.48,
    "duration": 6.56
  },
  {
    "text": "किंवा डोंगराच्या उताराला घसरत सुद्धा",
    "start_time": 250.08,
    "duration": 5.04
  },
  {
    "text": "मनुष्य जाऊ शकेल चालायची सुद्धा गरज लागत",
    "start_time": 253.04,
    "duration": 5.52
  },
  {
    "text": "नाही तेच शिखर गाठायचं म्हटलं की प्रत्येक",
    "start_time": 255.12,
    "duration": 6.799
  },
  {
    "text": "पावलाला घाम फुटतो",
    "start_time": 258.56,
    "duration": 7.68
  },
  {
    "text": "तसं हे देवत्वाच शिखर गाठायचं म्हणजे",
    "start_time": 261.919,
    "duration": 7.041
  },
  {
    "text": "त्यासाठी जी सद्वृत्ती लागते जी सद्बुद्धी",
    "start_time": 266.24,
    "duration": 5.28
  },
  {
    "text": "लागते जी सावधानता लागते ती दुर्लभ आहे",
    "start_time": 268.96,
    "duration": 5.679
  },
  {
    "text": "असं मला म्हणायचं आहे आपल्यासमोर",
    "start_time": 271.52,
    "duration": 6.48
  },
  {
    "text": "तेव्हा साधना किंवा वृत्तीपालट",
    "start_time": 274.639,
    "duration": 6.161
  },
  {
    "text": "या मार्गाला जरा वेळ लागतो ते खरं",
    "start_time": 278.0,
    "duration": 5.52
  },
  {
    "text": "नैसर्गिक काम आहे ते खरं आहे ते सगळेच",
    "start_time": 280.8,
    "duration": 6.24
  },
  {
    "text": "सत्पुरुष करीत असतात फक्त करण्याचे मार्ग",
    "start_time": 283.52,
    "duration": 6.56
  },
  {
    "text": "भिन्न असतात प्रत्येकाचे ते करण्याचे",
    "start_time": 287.04,
    "duration": 6.8
  },
  {
    "text": "मार्ग भिन्न आहेत त्यामुळं",
    "start_time": 290.08,
    "duration": 6.88
  },
  {
    "text": "वेगवेगळ्या मार्गांचे आणि भिन्न प्रकृतीचे",
    "start_time": 293.84,
    "duration": 4.72
  },
  {
    "text": "सत्पुरुष",
    "start_time": 296.96,
    "duration": 4.239
  },
  {
    "text": "ईश्वरी इच्छेन",
    "start_time": 298.56,
    "duration": 4.8
  },
  {
    "text": "इच्छेनुसार",
    "start_time": 301.199,
    "duration": 5.121
  },
  {
    "text": "येतात घडतात",
    "start_time": 303.36,
    "duration": 5.2
  },
  {
    "text": "आणि",
    "start_time": 306.32,
    "duration": 5.36
  },
  {
    "text": "आपला उद्धार करतात त्यांचा ती तळमळ आहे",
    "start_time": 308.56,
    "duration": 5.6
  },
  {
    "text": "प्रयत्न आहे",
    "start_time": 311.68,
    "duration": 5.6
  },
  {
    "text": "हे मार्ग वेगवेगळे वाढले तरी एक आतून",
    "start_time": 314.16,
    "duration": 6.64
  },
  {
    "text": "लक्षात ठेवावे की ते पूरक आहेत",
    "start_time": 317.28,
    "duration": 6.16
  },
  {
    "text": "जसं कर्म ज्ञान भक्ती योग हे वेगवेगळे",
    "start_time": 320.8,
    "duration": 4.32
  },
  {
    "text": "दिसतात",
    "start_time": 323.44,
    "duration": 4.8
  },
  {
    "text": "ते पूरक आहेत आतून एकमेकाला",
    "start_time": 325.12,
    "duration": 6.32
  },
  {
    "text": "सत्पुरुष असे वेगवेगळे भासले तरी ते हातून",
    "start_time": 328.24,
    "duration": 5.84
  },
  {
    "text": "पूरक असतात त्याच्या खुणा ते एकमेकांना",
    "start_time": 331.44,
    "duration": 5.52
  },
  {
    "text": "देत असतात",
    "start_time": 334.08,
    "duration": 6.88
  },
  {
    "text": "मुख्यतः जसे ईश्वरी कार्याचे वरून खाली",
    "start_time": 336.96,
    "duration": 7.76
  },
  {
    "text": "येण अवतरण आणि आरोहण असे दोन मार्ग आहेत",
    "start_time": 340.96,
    "duration": 6.64
  },
  {
    "text": "अवतरण आरोहण हे जसे दोन मार्ग आहेत खाली",
    "start_time": 344.72,
    "duration": 5.6
  },
  {
    "text": "येणं खालून वर जाणं कुठेतरी भगवंताची गाठ",
    "start_time": 347.6,
    "duration": 6.96
  },
  {
    "text": "पडू म्हणजे झालं एवढाच मुद्दा आहे तर तसं",
    "start_time": 350.32,
    "duration": 7.52
  },
  {
    "text": "अवतरण पत्करून",
    "start_time": 354.56,
    "duration": 6.24
  },
  {
    "text": "ते कार्य करणारे सत्पुरुष आहेत आरोहन",
    "start_time": 357.84,
    "duration": 6.479
  },
  {
    "text": "करायला लावून कार्य करणारे सत्पुरुष आहेत",
    "start_time": 360.8,
    "duration": 5.76
  },
  {
    "text": "वर चढत जाणार आरोहण",
    "start_time": 364.319,
    "duration": 5.521
  },
  {
    "text": "तर क्रमाक्रमाने टप्प्याटप्प्याने",
    "start_time": 366.56,
    "duration": 4.8
  },
  {
    "text": "तर",
    "start_time": 369.84,
    "duration": 5.04
  },
  {
    "text": "आपल्याला अगदी ठळक",
    "start_time": 371.36,
    "duration": 5.44
  },
  {
    "text": "म्हणजे खूप आहेत असंख्य आहेत पण तरी",
    "start_time": 374.88,
    "duration": 4.0
  },
  {
    "text": "सुद्धा एकदम ठळक ज्यांच्या परिचय आणि",
    "start_time": 376.8,
    "duration": 5.44
  },
  {
    "text": "जाणीव असते गजानन महाराज आहेत आपल्या",
    "start_time": 378.88,
    "duration": 6.319
  },
  {
    "text": "डोळ्यासमोर पटकन येत स्वामी महाराज आहेत",
    "start_time": 382.24,
    "duration": 5.679
  },
  {
    "text": "अक्कलकोट स्वामी महाराज आहेत",
    "start_time": 385.199,
    "duration": 4.321
  },
  {
    "text": "किंवा",
    "start_time": 387.919,
    "duration": 4.481
  },
  {
    "text": "साईबाबा आहेत",
    "start_time": 389.52,
    "duration": 6.16
  },
  {
    "text": "यांचा आपल्या लक्षात असेल किंवा तिकडे",
    "start_time": 392.4,
    "duration": 6.239
  },
  {
    "text": "यांचे गुरु नाथनंगे बाबा आहेत अशी मंडळी",
    "start_time": 395.68,
    "duration": 6.32
  },
  {
    "text": "आहेत ते आणि गजानन महाराज समकालीन आहे",
    "start_time": 398.639,
    "duration": 6.481
  },
  {
    "text": "तेव्हा असे सत्पुरुष आहे ते आपल्या लक्षात",
    "start_time": 402.0,
    "duration": 6.16
  },
  {
    "text": "येईल की ते",
    "start_time": 405.12,
    "duration": 6.16
  },
  {
    "text": "काम करतात त्याच काही वैशिष्ट्य आहे ते",
    "start_time": 408.16,
    "duration": 4.56
  },
  {
    "text": "वेगळे पण",
    "start_time": 411.28,
    "duration": 4.08
  },
  {
    "text": "अनेकदा ह्या तीन सत्पुरुषांच्या बाबतीत",
    "start_time": 412.72,
    "duration": 6.16
  },
  {
    "text": "आपण पाहिलं तर त्यांची आपल्याला ही प्रगटन",
    "start_time": 415.36,
    "duration": 6.959
  },
  {
    "text": "वगैरे करावे लागतात बाकीच काही इतिहास",
    "start_time": 418.88,
    "duration": 7.68
  },
  {
    "text": "सापडत नाही तो ते देतही नाही त्याच्या",
    "start_time": 422.319,
    "duration": 6.801
  },
  {
    "text": "मागे त्यांना तसं का करावं लागतं याचा आपण",
    "start_time": 426.56,
    "duration": 6.479
  },
  {
    "text": "भक्त म्हणून विचार केला का",
    "start_time": 429.12,
    "duration": 6.799
  },
  {
    "text": "त्यांना असं का करावा लागत बाकीच्या आपण",
    "start_time": 433.039,
    "duration": 4.961
  },
  {
    "text": "सगळ्या कुंडल्या मांडून बघितलेल्या आहेत",
    "start_time": 435.919,
    "duration": 4.56
  },
  {
    "text": "पण त्या आपल्या बाजूने झाले त्यात काही",
    "start_time": 438.0,
    "duration": 4.4
  },
  {
    "text": "निकाली निष्पन्न होत",
    "start_time": 440.479,
    "duration": 4.72
  },
  {
    "text": "कारण",
    "start_time": 442.4,
    "duration": 5.6
  },
  {
    "text": "आम्ही त्यांच एकदा कुळ",
    "start_time": 445.199,
    "duration": 6.641
  },
  {
    "text": "बघितलं गाठलं किंवा कळलं तर आमचे शक्य",
    "start_time": 448.0,
    "duration": 6.479
  },
  {
    "text": "त्याच्यावर उमटवायला जातो ज्याचे त्याचे",
    "start_time": 451.84,
    "duration": 5.28
  },
  {
    "text": "सत्पुरुष होऊन जातात त्यांना जे करायचं",
    "start_time": 454.479,
    "duration": 5.12
  },
  {
    "text": "नसतं ते नेमकं आम्ही त्यांना करायला लावतो",
    "start_time": 457.12,
    "duration": 5.6
  },
  {
    "text": "यासाठी हे मी कोण हेच सांगत नाहीत तुमचं",
    "start_time": 459.599,
    "duration": 6.481
  },
  {
    "text": "काय काम आहे ते सांगा एक काम करूया तुम्ही",
    "start_time": 462.72,
    "duration": 5.12
  },
  {
    "text": "याला काय सांगायचं ते काम मी सांगतो ते",
    "start_time": 466.08,
    "duration": 3.76
  },
  {
    "text": "तुम्ही करा बघा गजानन महाराजांनी तेच",
    "start_time": 467.84,
    "duration": 3.759
  },
  {
    "text": "सांगितलं ते स्वामी महाराज महाराजांनी",
    "start_time": 469.84,
    "duration": 3.68
  },
  {
    "text": "सांगितल तेच साहेबांनी सांगितल बाकीचं काय",
    "start_time": 471.599,
    "duration": 4.32
  },
  {
    "text": "करायचं मी हिंदू आहे का मुसलमान आहे का",
    "start_time": 473.52,
    "duration": 4.0
  },
  {
    "text": "अमुक आहे कांगी आहे का ब्राह्मण आहे का",
    "start_time": 475.919,
    "duration": 3.921
  },
  {
    "text": "अमुक आहे ते काय त्याच्याशी काम काय आहे",
    "start_time": 477.52,
    "duration": 5.2
  },
  {
    "text": "मूळ काय काम आहे ते त्याच्यासाठी खर",
    "start_time": 479.84,
    "duration": 6.96
  },
  {
    "text": "म्हणजे त्यांचा जीव तो अशाही सत्पुरुषांचा",
    "start_time": 482.72,
    "duration": 9.24
  },
  {
    "text": "तेव्हा प्रकट होण एकदम",
    "start_time": 486.8,
    "duration": 5.16
  },
  {
    "text": "त्याच्यावर सुके पडू नयेत म्हणून बाकी",
    "start_time": 492.8,
    "duration": 6.079
  },
  {
    "text": "काही माहिती न देणं घडविलक्षण ठिकाणी जाऊन",
    "start_time": 495.039,
    "duration": 6.801
  },
  {
    "text": "कुठेतरी राहणं कुठूनतरी मी आलो आहे म्हणून",
    "start_time": 498.879,
    "duration": 4.961
  },
  {
    "text": "सांगण",
    "start_time": 501.84,
    "duration": 6.16
  },
  {
    "text": "जशी या सगळ्यांच्या बाबतीत आपल्याला आढळेल",
    "start_time": 503.84,
    "duration": 8.319
  },
  {
    "text": "तसे इकडे महाराज आहेत तुकोबा आहेत",
    "start_time": 508.0,
    "duration": 7.2
  },
  {
    "text": "काल आपण परवाले गेल्या वेळेला आपण",
    "start_time": 512.159,
    "duration": 4.8
  },
  {
    "text": "पुण्यतिथीच्या निमित्ताने पाहिल बिडकर",
    "start_time": 515.2,
    "duration": 4.8
  },
  {
    "text": "महाराज आहेत",
    "start_time": 516.959,
    "duration": 5.52
  },
  {
    "text": "यांची आरोहणाची पद्धत आहे हळूहळू आहे",
    "start_time": 520.0,
    "duration": 4.72
  },
  {
    "text": "तिथून एक एक पायरी आपल्याला घेऊन जातील",
    "start_time": 522.479,
    "duration": 5.521
  },
  {
    "text": "जसं या दोन मध्ये फरक आहे तस त्यांच्या",
    "start_time": 524.72,
    "duration": 6.0
  },
  {
    "text": "कार्यपद्धतीत सुद्धा फरक आहे आपण पाहिला",
    "start_time": 528.0,
    "duration": 8.8
  },
  {
    "text": "असेल तर हे असे अवतारी पुरुष आहेत त्यांचा",
    "start_time": 530.72,
    "duration": 10.799
  },
  {
    "text": "भर लीलेवर आहे अद्भुतेवर आहे कळत नाही",
    "start_time": 536.8,
    "duration": 7.76
  },
  {
    "text": "आपल्याला काही उलगडत नाही",
    "start_time": 541.519,
    "duration": 5.361
  },
  {
    "text": "यांच काही सगळं उलगड अशातला भाग नाही तरी",
    "start_time": 544.56,
    "duration": 8.76
  },
  {
    "text": "सुद्धा उलगडल्यासारखं वाटते आपण समजून सगळ",
    "start_time": 546.88,
    "duration": 6.44
  },
  {
    "text": "त्यांची भाषा वेगळी असते बोलतात ते",
    "start_time": 553.76,
    "duration": 5.199
  },
  {
    "text": "वाक्याचा अर्थ खूप दिवसांनी वर्षांनी",
    "start_time": 556.64,
    "duration": 3.84
  },
  {
    "text": "लागतो",
    "start_time": 558.959,
    "duration": 4.401
  },
  {
    "text": "गुढ असतं सूचक असतं",
    "start_time": 560.48,
    "duration": 5.52
  },
  {
    "text": "उधरण्याचे मार्ग सुद्धा या अशा अवतारी",
    "start_time": 563.36,
    "duration": 5.36
  },
  {
    "text": "पुरुषांचे हे अनेकदा नुसत्या सेवेचे असतात",
    "start_time": 566.0,
    "duration": 5.519
  },
  {
    "text": "एखाद्या आज्ञेचे असतात त्यांच्या खुणा",
    "start_time": 568.72,
    "duration": 6.559
  },
  {
    "text": "देण्याच्या पद्धती वेगळ्या असतात",
    "start_time": 571.519,
    "duration": 6.561
  },
  {
    "text": "इकडे मात्र हे जे सत्पुरुष काम करतात हे",
    "start_time": 575.279,
    "duration": 4.721
  },
  {
    "text": "सगळे ते एकच काम करतात सगळ्यांची इच्छा",
    "start_time": 578.08,
    "duration": 3.68
  },
  {
    "text": "एवढीच आहे की माणसाचा देव व्हावा त्याला",
    "start_time": 580.0,
    "duration": 3.68
  },
  {
    "text": "देवाची गाठ पडावी तो आनंदात राहावा",
    "start_time": 581.76,
    "duration": 4.56
  },
  {
    "text": "समाधानात राहावा त्याच या कचाट्यातून",
    "start_time": 583.68,
    "duration": 5.04
  },
  {
    "text": "मुक्तता व्हावी या पलीकडे त्यांना कोणालाच",
    "start_time": 586.32,
    "duration": 5.28
  },
  {
    "text": "काही वेळवायचं नाही वेगळं हे नक्की लक्षात",
    "start_time": 588.72,
    "duration": 8.64
  },
  {
    "text": "ठेवून आपल्याला लगेच फरक आढळेल या हे जे",
    "start_time": 591.6,
    "duration": 7.76
  },
  {
    "text": "आपल्या वावरून माहिती असलेल्या अशा",
    "start_time": 597.36,
    "duration": 5.52
  },
  {
    "text": "स्वरूपाचे महापुरुष आहेत सत्पुरुष आहेत",
    "start_time": 599.36,
    "duration": 9.44
  },
  {
    "text": "त्यांचा भर बोधावर आहे फरक आढळ उपदेशावर",
    "start_time": 602.88,
    "duration": 8.48
  },
  {
    "text": "आहे समजावून देण्यावर आहे त्याच्या गतीने",
    "start_time": 608.8,
    "duration": 7.52
  },
  {
    "text": "जाण्यावर आहे ग्रंथ लेखनावर आहे खूप आहेत",
    "start_time": 611.36,
    "duration": 7.44
  },
  {
    "text": "पद लिहितील अभंग लिहतील काहीतरी करून ते",
    "start_time": 616.32,
    "duration": 5.12
  },
  {
    "text": "त्या मार्गाने त्याचं उन्नयन कसं होईल एवढ",
    "start_time": 618.8,
    "duration": 5.36
  },
  {
    "text": "पाहतील त्याची वृत्ती जी अडकली आहे",
    "start_time": 621.44,
    "duration": 6.079
  },
  {
    "text": "प्रपंचात मोकळी कशी होईल ते पाहतील",
    "start_time": 624.16,
    "duration": 6.239
  },
  {
    "text": "साधनेचा मार्ग घालून देतील स्वतः आचरून",
    "start_time": 627.519,
    "duration": 4.961
  },
  {
    "text": "दाखवतील इकडे सगळं तसं आहे त्यांच्या",
    "start_time": 630.399,
    "duration": 4.081
  },
  {
    "text": "आचरणाशी वगैरे आपण तिकडे काय बघायला जायचं",
    "start_time": 632.48,
    "duration": 5.76
  },
  {
    "text": "नाही ते काय करतील केव्हा ते तेच जाणत आणि",
    "start_time": 634.48,
    "duration": 6.88
  },
  {
    "text": "कशासाठी करतील ते ही तेच जाणत होतं ज्याचं",
    "start_time": 638.24,
    "duration": 5.36
  },
  {
    "text": "काम असतं त्याला ते कळतं एवढी गोष्ट खरी",
    "start_time": 641.36,
    "duration": 4.88
  },
  {
    "text": "तेव्हा स्वामींच्या बाबतीत आपण पाहिलं",
    "start_time": 643.6,
    "duration": 8.4
  },
  {
    "text": "असेल तर असं बोध उपदेश आचरण ग्रंथ हे",
    "start_time": 646.24,
    "duration": 9.12
  },
  {
    "text": "भानगड नाही काय असेल ते थेट खांब चला असं",
    "start_time": 652.0,
    "duration": 8.88
  },
  {
    "text": "आहे तर त्यामुळे त्यांच्या लीला किंवा",
    "start_time": 655.36,
    "duration": 7.84
  },
  {
    "text": "त्याच स्मरण करणं",
    "start_time": 660.88,
    "duration": 5.199
  },
  {
    "text": "मार्ग तीन असतात अशा महापुरुषांच्याकडे",
    "start_time": 663.2,
    "duration": 5.199
  },
  {
    "text": "जेव्हा अवतारी महापुरुषांच्या कडे आपण",
    "start_time": 666.079,
    "duration": 6.88
  },
  {
    "text": "जातो तेव्हा इकडे कसं बोध असतो सांगितले",
    "start_time": 668.399,
    "duration": 7.281
  },
  {
    "text": "असत रोजच प्रवचन दैनंदिन आपल्याला वाचन",
    "start_time": 672.959,
    "duration": 5.601
  },
  {
    "text": "मोकळ सोप करून दिलेले आपल्या गतीने बरोबर",
    "start_time": 675.68,
    "duration": 4.719
  },
  {
    "text": "चाललेले आहेत काय अडचणी आहेत बरोबर माहिती",
    "start_time": 678.56,
    "duration": 4.08
  },
  {
    "text": "आहे प्रापंचिक कुठे अडकणार कुठे घोडा",
    "start_time": 680.399,
    "duration": 5.041
  },
  {
    "text": "अडकळतो ना तस आहे ते कुठे अडकळत ते बरोबर",
    "start_time": 682.64,
    "duration": 4.96
  },
  {
    "text": "त्या घोडे स्वराला जस माहिती असतं तस",
    "start_time": 685.44,
    "duration": 3.76
  },
  {
    "text": "प्रापंचिक मनुष्य कुठे अडकेल बरोबर",
    "start_time": 687.6,
    "duration": 3.28
  },
  {
    "text": "त्यांना माहिती असत हे सत्पुरुष आपल्याला",
    "start_time": 689.2,
    "duration": 4.4
  },
  {
    "text": "जवळचे कापडतात ते यामुळे पडतात आणि ते",
    "start_time": 690.88,
    "duration": 6.32
  },
  {
    "text": "वाटतात तसे ते करतात काम तेच पण हे ज्या",
    "start_time": 693.6,
    "duration": 5.6
  },
  {
    "text": "पद्धतीने करतात त्या पद्धतीने ते हे करत",
    "start_time": 697.2,
    "duration": 4.639
  },
  {
    "text": "नाहीत एवढाच फक्त फरक आपल्याला हा वरवर",
    "start_time": 699.2,
    "duration": 6.16
  },
  {
    "text": "दिसणारा कळू शकणार आहे अशा अवतारी",
    "start_time": 701.839,
    "duration": 4.801
  },
  {
    "text": "पुरुषांच्याकडे काय मार्ग असतात",
    "start_time": 705.36,
    "duration": 4.08
  },
  {
    "text": "सत्याबद्दल बोलत होतो एक त्यांच्या ज्या",
    "start_time": 706.64,
    "duration": 5.04
  },
  {
    "text": "लीला आहेत त्यांचं स्मरण करावं काहीतरी",
    "start_time": 709.44,
    "duration": 4.399
  },
  {
    "text": "त्याचं चित्तावर ठसाव वाटतं की अरे हे",
    "start_time": 711.68,
    "duration": 5.52
  },
  {
    "text": "जगामध्ये शक्य आहे होऊ शकतं यांच्या",
    "start_time": 713.839,
    "duration": 5.201
  },
  {
    "text": "संकल्पाने सुद्धा हे होऊ शकतं यांच्या",
    "start_time": 717.2,
    "duration": 4.4
  },
  {
    "text": "एखाद्या शब्दाने होऊ शकत यांच्या एखाद्या",
    "start_time": 719.04,
    "duration": 5.44
  },
  {
    "text": "इच्छेने होऊ शकत नुसत्या सांगितलय म्हणून",
    "start_time": 721.6,
    "duration": 6.56
  },
  {
    "text": "होईल काही होईल असं तर हे अशा तऱहेच",
    "start_time": 724.48,
    "duration": 8.56
  },
  {
    "text": "लीलांच्या स्मरणामुळे भगवंताची झलक मिळते",
    "start_time": 728.16,
    "duration": 7.119
  },
  {
    "text": "लीलांच्या स्मरणामध्ये त्यासाठी",
    "start_time": 733.04,
    "duration": 5.12
  },
  {
    "text": "त्यांच्याकडे जायचं असेल तर अशा भावनेने",
    "start_time": 735.279,
    "duration": 6.081
  },
  {
    "text": "जाव लीलांच स्मरण कराव",
    "start_time": 738.16,
    "duration": 5.359
  },
  {
    "text": "त्यामध्ये",
    "start_time": 741.36,
    "duration": 4.56
  },
  {
    "text": "आपल्याला कुठे कुठे बोध शोधावा लागतो तो",
    "start_time": 743.519,
    "duration": 6.56
  },
  {
    "text": "शोधून मिळवा बोध नसतो अस होण शक्य नाही तर",
    "start_time": 745.92,
    "duration": 6.8
  },
  {
    "text": "असतोच इथे उघड मांडून ठेवलेला आहे आणि",
    "start_time": 750.079,
    "duration": 5.281
  },
  {
    "text": "तिथे तुम्ही शोधून घ्यायचा आहे प्रसंगातून",
    "start_time": 752.72,
    "duration": 5.44
  },
  {
    "text": "शोधून घ्यायचा आहे असा दुसरा मार्ग आहे",
    "start_time": 755.36,
    "duration": 5.12
  },
  {
    "text": "आणि तिसरा मार्ग अवतारी पुरुषांच्याकडे",
    "start_time": 758.16,
    "duration": 3.919
  },
  {
    "text": "जायचा असेल स्वामींच्या सारख्या ज्यांचे",
    "start_time": 760.48,
    "duration": 6.32
  },
  {
    "text": "स्मरण करतो आहोत आज तिसरा मार्ग हा की",
    "start_time": 762.079,
    "duration": 9.841
  },
  {
    "text": "निष्ठा ठेवायची बस श्रद्धा हा विचारल काय",
    "start_time": 766.8,
    "duration": 7.039
  },
  {
    "text": "खड्यात पडू नाहीतर रस्त्याने जाव नाही तर",
    "start_time": 771.92,
    "duration": 4.88
  },
  {
    "text": "पाय मोडू नाही भराव काय होईल ते हो",
    "start_time": 773.839,
    "duration": 6.0
  },
  {
    "text": "निष्ठेने श्रद्धेने राहणार तेव्हा हाही",
    "start_time": 776.8,
    "duration": 5.599
  },
  {
    "text": "मार्ग त्यांच्याकडे जाऊन काही आपला उद्धार",
    "start_time": 779.839,
    "duration": 5.361
  },
  {
    "text": "करून घ्यायचा असेल तर",
    "start_time": 782.399,
    "duration": 4.56
  },
  {
    "text": "त्यातला बोध शोधून घ्यावा लागतो असं",
    "start_time": 785.2,
    "duration": 4.079
  },
  {
    "text": "म्हटलं आणि लीलांच स्मरण करावा लागतो असं",
    "start_time": 786.959,
    "duration": 4.961
  },
  {
    "text": "म्हटलं तसं फक्त थोडक्यात प्रत्येकाच",
    "start_time": 789.279,
    "duration": 6.161
  },
  {
    "text": "काहीतरी करतो स्मरण आपल्यासमोर",
    "start_time": 791.92,
    "duration": 6.159
  },
  {
    "text": "शोधावा लागतो कधीतरी एखाद वाक्य म्हणाले",
    "start_time": 795.44,
    "duration": 5.6
  },
  {
    "text": "असेल तर लक्षात ठेवावे लागतं स्वामी",
    "start_time": 798.079,
    "duration": 6.88
  },
  {
    "text": "महाराज म्हणाले शेत पिकून खाव आपल्याने",
    "start_time": 801.04,
    "duration": 7.84
  },
  {
    "text": "आपलं शेत पिकून खावं त्यांना आवडत आता",
    "start_time": 804.959,
    "duration": 6.481
  },
  {
    "text": "कुणाच शेत आहे तेव्हा",
    "start_time": 808.88,
    "duration": 5.44
  },
  {
    "text": "काय आपण पिकवणार आजच्या काळात का आम्ही",
    "start_time": 811.44,
    "duration": 6.24
  },
  {
    "text": "त्यातून पुढे त्याच्यावर जगणार शेवटी",
    "start_time": 814.32,
    "duration": 6.88
  },
  {
    "text": "आम्ही पिशव्या घेऊन दुकानात जाणार",
    "start_time": 817.68,
    "duration": 6.56
  },
  {
    "text": "तरी लिहून देणार ऑर्डर लिहून पडणार",
    "start_time": 821.2,
    "duration": 6.96
  },
  {
    "text": "तेव्हा शोधावा लागतो बोध तसं आपल शेत",
    "start_time": 824.24,
    "duration": 8.0
  },
  {
    "text": "शोधाव लागत तिकडे नाही बाहेर ते कुठे",
    "start_time": 828.16,
    "duration": 6.479
  },
  {
    "text": "पसरलेल नाहीये",
    "start_time": 832.24,
    "duration": 6.32
  },
  {
    "text": "ते क्षेत्रज्ञ योग साध्या भाषेत सांगतात",
    "start_time": 834.639,
    "duration": 6.401
  },
  {
    "text": "तेव्हा हे क्षेत्र",
    "start_time": 838.56,
    "duration": 6.24
  },
  {
    "text": "कोणी क्षेत्रज्ञ आहे जाणणारा जो आपल्या",
    "start_time": 841.04,
    "duration": 7.599
  },
  {
    "text": "ओळखू शकतो आपली परिस्थिती ओळखू शकतो",
    "start_time": 844.8,
    "duration": 6.88
  },
  {
    "text": "अंतर्याम अंतरंग ओळखू शकतो त्याने ते",
    "start_time": 848.639,
    "duration": 6.081
  },
  {
    "text": "ओळखावं आणि त्यातून ते पिकवून खाव म्हणजे",
    "start_time": 851.68,
    "duration": 4.8
  },
  {
    "text": "त्यातल्या प्रत्येक गोष्टीचा कसा",
    "start_time": 854.72,
    "duration": 5.44
  },
  {
    "text": "भगवंताकडे वापर करता येईल जाण्यासाठी",
    "start_time": 856.48,
    "duration": 6.159
  },
  {
    "text": "आणि जिथे कुठे अडकलो ते शोधून काढता येईल",
    "start_time": 860.16,
    "duration": 4.96
  },
  {
    "text": "आणि ते कसं मोकळं करता येईल हे शेत",
    "start_time": 862.639,
    "duration": 6.0
  },
  {
    "text": "पिकवायचं काम आहे शेत पिकवून खावं अशा",
    "start_time": 865.12,
    "duration": 6.0
  },
  {
    "text": "तऱने स्वतःला मिळालेल्या सर्व शक्ती",
    "start_time": 868.639,
    "duration": 4.88
  },
  {
    "text": "बुद्धींचा वापर",
    "start_time": 871.12,
    "duration": 3.92
  },
  {
    "text": "ते शेताचं पिकवायचं म्हणजे आपल्याला",
    "start_time": 873.519,
    "duration": 3.281
  },
  {
    "text": "माहिती आहे नांगरटी पासून सगळं करावं",
    "start_time": 875.04,
    "duration": 4.159
  },
  {
    "text": "लागतं मला सांगा पृथ्वीला एखादी नांगरट",
    "start_time": 876.8,
    "duration": 4.8
  },
  {
    "text": "होते",
    "start_time": 879.199,
    "duration": 5.681
  },
  {
    "text": "त्या वेळेला काय होतं याचा आपण विचार करा",
    "start_time": 881.6,
    "duration": 6.239
  },
  {
    "text": "शेत पिकून खाव म्हणजे बोध कसा असतो आणि तो",
    "start_time": 884.88,
    "duration": 6.56
  },
  {
    "text": "शोधावा कसा लागतो आपल्याला सुद्धा अनेक",
    "start_time": 887.839,
    "duration": 6.401
  },
  {
    "text": "प्रसंगांच्या निमित्ताने आपल्या मनाची",
    "start_time": 891.44,
    "duration": 6.48
  },
  {
    "text": "नांगरट होत असते बघितल असेल एक मन दिले पण",
    "start_time": 894.24,
    "duration": 5.36
  },
  {
    "text": "इतक्या मनाविरुद्ध गोष्टी ज्यावेळेला",
    "start_time": 897.92,
    "duration": 4.719
  },
  {
    "text": "होतात त्यावेळेला प्रसंगाची नांगरट होते",
    "start_time": 899.6,
    "duration": 6.16
  },
  {
    "text": "माणसाची पृथ्वीला फळ लागतो नांगराचा",
    "start_time": 902.639,
    "duration": 5.44
  },
  {
    "text": "आपल्याला माहिती असेल त्यावेळेला आपण",
    "start_time": 905.76,
    "duration": 4.639
  },
  {
    "text": "कल्पना करा आपल्याला एखादी टाचणी टोचली तर",
    "start_time": 908.079,
    "duration": 4.32
  },
  {
    "text": "काय होत असेल त्यावेळेला पृथ्वीला काय होत",
    "start_time": 910.399,
    "duration": 4.481
  },
  {
    "text": "असेल याची आपण कल्पना करावी म्हणजे शेत",
    "start_time": 912.399,
    "duration": 4.8
  },
  {
    "text": "पिकवण म्हणजे काय ते आपल्या लक्षात येतं",
    "start_time": 914.88,
    "duration": 4.88
  },
  {
    "text": "की आपल्या आपल्याला हे करायचं ना एकदा",
    "start_time": 917.199,
    "duration": 5.361
  },
  {
    "text": "गुरुच्या मार्गात जर गेलात तर ते करायला",
    "start_time": 919.76,
    "duration": 6.56
  },
  {
    "text": "मिळणारच नाही ते म्हणतील ते कराव लागेल",
    "start_time": 922.56,
    "duration": 8.079
  },
  {
    "text": "मी घेईन तर ते म्हणे काढून घेईन अस सगळ",
    "start_time": 926.32,
    "duration": 6.56
  },
  {
    "text": "होतो त्यावेळेला आपली आपली नांगरट होत",
    "start_time": 930.639,
    "duration": 4.401
  },
  {
    "text": "असते शेताची हे हव म्हणल की ती नको",
    "start_time": 932.88,
    "duration": 4.16
  },
  {
    "text": "म्हणणार ते पाहिजे म्हटल की देत नाही",
    "start_time": 935.04,
    "duration": 4.64
  },
  {
    "text": "म्हणणार त्यात हेतू एवढाच असतो फक्त की",
    "start_time": 937.04,
    "duration": 4.96
  },
  {
    "text": "ह्याला उकलून काढाव अडकलेले सगळे",
    "start_time": 939.68,
    "duration": 4.399
  },
  {
    "text": "पहिल्यांदा नांगरट करताना सुद्धा अनेकदा",
    "start_time": 942.0,
    "duration": 5.279
  },
  {
    "text": "खाली तण लागलेल असत किती गवत उगवलेल असत",
    "start_time": 944.079,
    "duration": 5.76
  },
  {
    "text": "सगळं काढून जेव्हा मोकळं करावं तेव्हा",
    "start_time": 947.279,
    "duration": 5.281
  },
  {
    "text": "तिथं काहीतरी पेरता येतं तर तसं आपल्याकडे",
    "start_time": 949.839,
    "duration": 6.0
  },
  {
    "text": "पहिल्या अनेक जन्मांच नांगरला लागत",
    "start_time": 952.56,
    "duration": 5.68
  },
  {
    "text": "त्यावेळेला वर येत अनेक जन्मांच ते सगळं",
    "start_time": 955.839,
    "duration": 5.281
  },
  {
    "text": "काढून फेकून द्याव लागत अहंकाराने अडकलेल",
    "start_time": 958.24,
    "duration": 5.519
  },
  {
    "text": "आहे स्मरणाने अडकलेला आहे मताने अडकलेला",
    "start_time": 961.12,
    "duration": 5.12
  },
  {
    "text": "आग्रहाने अडकलेल हे सगळीकडून जे सगळं",
    "start_time": 963.759,
    "duration": 5.921
  },
  {
    "text": "चित्त झालेल असतं अमुक करीन तमुक करीन हे",
    "start_time": 966.24,
    "duration": 5.44
  },
  {
    "text": "सगळे अहंकाराचे पुन्हा आविष्कार झालेले",
    "start_time": 969.68,
    "duration": 5.68
  },
  {
    "text": "असतात ते सगळे नांगरून एक एक बाजूला करावं",
    "start_time": 971.68,
    "duration": 6.399
  },
  {
    "text": "तशी नांगरट चित्ताची होते त्यावेळेला ते",
    "start_time": 975.36,
    "duration": 6.399
  },
  {
    "text": "पेरण्या योग्य होतं मग बोध पेरावा आणि",
    "start_time": 978.079,
    "duration": 7.041
  },
  {
    "text": "त्याला लागणारा भाव आणि कृती यांची जोड",
    "start_time": 981.759,
    "duration": 6.961
  },
  {
    "text": "देऊन मग ते भावाने पाण्याने ते वाढायला",
    "start_time": 985.12,
    "duration": 6.959
  },
  {
    "text": "लागत खर खर पिकत आणि मग ते पिकून खाव",
    "start_time": 988.72,
    "duration": 6.4
  },
  {
    "text": "म्हणजे आनंदाने राहाव पुढे ते करता येत",
    "start_time": 992.079,
    "duration": 5.841
  },
  {
    "text": "तेव्हा स्वामी महाराज जस म्हणाले तस आपली",
    "start_time": 995.12,
    "duration": 5.6
  },
  {
    "text": "सूचकता लक्षात घेऊन जा दुसरं",
    "start_time": 997.92,
    "duration": 5.279
  },
  {
    "text": "त्यांच्याकडून या लीलांच्या निमित्ताने",
    "start_time": 1000.72,
    "duration": 5.919
  },
  {
    "text": "काय शिकावं तर काडीचा सुद्धा अभिमान",
    "start_time": 1003.199,
    "duration": 7.281
  },
  {
    "text": "बाळगता येत नाही शिका गर्व करता येत नाही",
    "start_time": 1006.639,
    "duration": 6.161
  },
  {
    "text": "शिका",
    "start_time": 1010.48,
    "duration": 6.039
  },
  {
    "text": "रामेश्वर जवळ",
    "start_time": 1012.8,
    "duration": 3.719
  },
  {
    "text": "दोन गाव आहेत शिवकांची विष्णुकांची",
    "start_time": 1016.56,
    "duration": 7.639
  },
  {
    "text": "त्यांची ना",
    "start_time": 1020.48,
    "duration": 3.719
  },
  {
    "text": "तेव्हा",
    "start_time": 1024.319,
    "duration": 3.921
  },
  {
    "text": "वैष्णव मंडळी आहेत त्यांना वंश परंपरा",
    "start_time": 1025.839,
    "duration": 4.801
  },
  {
    "text": "इनाम मिळालेली गाव आहेत",
    "start_time": 1028.24,
    "duration": 5.76
  },
  {
    "text": "तिथलं सगळं उत्पन्न त्यांचा आहे सगळा",
    "start_time": 1030.64,
    "duration": 7.12
  },
  {
    "text": "अधिकार त्यांचा आहे इनामाची आहे गोष्ट खरी",
    "start_time": 1034.0,
    "duration": 6.959
  },
  {
    "text": "पण या गोष्टीने म्हणजे जी गोष्ट इनाम",
    "start_time": 1037.76,
    "duration": 5.919
  },
  {
    "text": "म्हणून मिळालेली आहे तिचा सुद्धा थूर",
    "start_time": 1040.959,
    "duration": 6.72
  },
  {
    "text": "माणसाच्या येतो डोळ्यावर तिची सुद्धा आड",
    "start_time": 1043.679,
    "duration": 6.081
  },
  {
    "text": "येते वास्तविक खरं सांगायचं ना तर हे",
    "start_time": 1047.679,
    "duration": 5.521
  },
  {
    "text": "सुद्धा सगळं इनामच आहे",
    "start_time": 1049.76,
    "duration": 5.68
  },
  {
    "text": "काय मला सांगा पैसा टाकला कुठला आणि काय",
    "start_time": 1053.2,
    "duration": 5.599
  },
  {
    "text": "विकत घेतला डोळा विकत घेतला आज किंमत कळेल",
    "start_time": 1055.44,
    "duration": 5.92
  },
  {
    "text": "डोळ्याशी बाहेर गेल्यावर काय आहे एका",
    "start_time": 1058.799,
    "duration": 4.481
  },
  {
    "text": "मोतीबिनूची किंमत सध्या किती असते काय मला",
    "start_time": 1061.36,
    "duration": 3.92
  },
  {
    "text": "काय माहित नाही द हजार तरी असेल सध्या",
    "start_time": 1063.28,
    "duration": 6.8
  },
  {
    "text": "काढायचा झाला तर आपल्याला माहिती तसं हे",
    "start_time": 1065.28,
    "duration": 7.44
  },
  {
    "text": "प्रत्यभ",
    "start_time": 1070.08,
    "duration": 5.92
  },
  {
    "text": "बाळगून गोष्ट खरी जाणीव बाळगावी एवढ्या",
    "start_time": 1072.72,
    "duration": 6.4
  },
  {
    "text": "गोष्टी इनामात मिळालेल्या आहेत तेव्हा",
    "start_time": 1076.0,
    "duration": 4.96
  },
  {
    "text": "त्या त्यांच्या सेवेसाठी वापरण्यासाठी",
    "start_time": 1079.12,
    "duration": 4.799
  },
  {
    "text": "असतात इनाम असतात कशासाठी",
    "start_time": 1080.96,
    "duration": 5.599
  },
  {
    "text": "की ते देवस्थानाची जी सेवा आहे ती",
    "start_time": 1083.919,
    "duration": 6.561
  },
  {
    "text": "मनःपूर्वक करायला जो वेळ लागतो",
    "start_time": 1086.559,
    "duration": 6.0
  },
  {
    "text": "आपण सावदगिरीन",
    "start_time": 1090.48,
    "duration": 4.16
  },
  {
    "text": "ताना",
    "start_time": 1092.559,
    "duration": 4.801
  },
  {
    "text": "की हे सगळं देवाची सेवा करायला वेळ लागतो",
    "start_time": 1094.64,
    "duration": 6.08
  },
  {
    "text": "प्रपंचा पुढे तो वेळ मिळत नाही माणसाला आज",
    "start_time": 1097.36,
    "duration": 5.12
  },
  {
    "text": "प्रपंचा पुढे आपल्याला दहा मिनिटाची",
    "start_time": 1100.72,
    "duration": 3.68
  },
  {
    "text": "देवपूजा 20 मिनिटाची देवपूजा करायची वेळ",
    "start_time": 1102.48,
    "duration": 5.12
  },
  {
    "text": "येते ज्याला देवस्थान सांभाळायचा आहे",
    "start_time": 1104.4,
    "duration": 5.6
  },
  {
    "text": "त्याला त्याच्यासाठी किती वेळ द्यावा",
    "start_time": 1107.6,
    "duration": 5.04
  },
  {
    "text": "लागेल मग तो प्रपंच कधी करील त्याच्या",
    "start_time": 1110.0,
    "duration": 6.64
  },
  {
    "text": "पोटाच कसं होईल म्हणून इनाम दिल",
    "start_time": 1112.64,
    "duration": 5.68
  },
  {
    "text": "की त्यावर त्याला उत्पन्न मिळेल",
    "start_time": 1116.64,
    "duration": 3.6
  },
  {
    "text": "त्याच्यावर तो राहील त्याच्यात येणार",
    "start_time": 1118.32,
    "duration": 3.52
  },
  {
    "text": "पुन्हा उत्पन्न असेल त्याच्यावर राहील",
    "start_time": 1120.24,
    "duration": 5.92
  },
  {
    "text": "म्हणून इनाम दिली अशी पद्धत होती तेव्हा",
    "start_time": 1121.84,
    "duration": 7.44
  },
  {
    "text": "वैष्णवाना इनाम दिली",
    "start_time": 1126.16,
    "duration": 4.879
  },
  {
    "text": "त त्याचे",
    "start_time": 1129.28,
    "duration": 6.48
  },
  {
    "text": "थोडा धूर कारण फुकट आल खर सांगायचं तर",
    "start_time": 1131.039,
    "duration": 7.601
  },
  {
    "text": "काही मिळू नये अस मला वाटत अनेकदा एवढीची",
    "start_time": 1135.76,
    "duration": 4.72
  },
  {
    "text": "गोष्ट असेल तरी सुद्धा किंमत मोजून मिळावी",
    "start_time": 1138.64,
    "duration": 4.48
  },
  {
    "text": "म्हणजे तिचे लक्षात राहत काय ते आणि उपयोग",
    "start_time": 1140.48,
    "duration": 5.52
  },
  {
    "text": "बरोबर कसा करावा हे पुढे भान राहत त्या",
    "start_time": 1143.12,
    "duration": 5.679
  },
  {
    "text": "गोष्टीच म्हणून",
    "start_time": 1146.0,
    "duration": 5.6
  },
  {
    "text": "ते गेलं की काय होतं ते स्वामींच्याकडे",
    "start_time": 1148.799,
    "duration": 4.88
  },
  {
    "text": "गेल्यावर कळत",
    "start_time": 1151.6,
    "duration": 3.92
  },
  {
    "text": "तेव्हा हा धूर लक्षात आला स्वामी",
    "start_time": 1153.679,
    "duration": 5.641
  },
  {
    "text": "त्यावेळेला तिथे होते",
    "start_time": 1155.52,
    "duration": 3.8
  },
  {
    "text": "वंश परंपरा ज्या गोष्टी आल्या",
    "start_time": 1159.36,
    "duration": 7.28
  },
  {
    "text": "शिवगांजेमध्ये स्वामींच वास्तव्य असताना",
    "start_time": 1163.039,
    "duration": 5.601
  },
  {
    "text": "ते पाहिल सगळ",
    "start_time": 1166.64,
    "duration": 5.039
  },
  {
    "text": "आणि एक दिवशी सरकारी हुकूम झाला हे सगळे",
    "start_time": 1168.64,
    "duration": 5.52
  },
  {
    "text": "हे जे महापुरुष आहेत साधारणते अठरा",
    "start_time": 1171.679,
    "duration": 4.641
  },
  {
    "text": "सालापर्यंत हा काळ आहे त्याच्या मागे शंभर",
    "start_time": 1174.16,
    "duration": 3.519
  },
  {
    "text": "वर्ष",
    "start_time": 1176.32,
    "duration": 3.68
  },
  {
    "text": "अगदी महाराजांचा काळ आहे गजानन महाराजांचा",
    "start_time": 1177.679,
    "duration": 5.441
  },
  {
    "text": "काळ आहे सगळ्यांचा सगळ्यांचे काळ असे ते",
    "start_time": 1180.0,
    "duration": 6.4
  },
  {
    "text": "काळ आहेत त्या काळात त्या महापुरुषांना",
    "start_time": 1183.12,
    "duration": 7.12
  },
  {
    "text": "दोन गोष्टींची छायेखाली सतत वावराव",
    "start_time": 1186.4,
    "duration": 6.32
  },
  {
    "text": "लागलेले आहे एकच्या खाली वावरत नाही वर",
    "start_time": 1190.24,
    "duration": 4.64
  },
  {
    "text": "असतात फक्त आपल्याला आपल्याकडून आम्ही वर",
    "start_time": 1192.72,
    "duration": 5.12
  },
  {
    "text": "पाहायचं म्हणून बघायचं वर दिसत एवढच एक",
    "start_time": 1194.88,
    "duration": 5.76
  },
  {
    "text": "बाजूनी मोंगलाई दुसऱ्या बाजू ब्रिटिश काळ",
    "start_time": 1197.84,
    "duration": 6.16
  },
  {
    "text": "आहे अंगलाई मोंगलाई खाली त्यांना वावराव",
    "start_time": 1200.64,
    "duration": 6.32
  },
  {
    "text": "लागलं त्या परिस्थितीमध्ये कसं वातावरण",
    "start_time": 1204.0,
    "duration": 5.36
  },
  {
    "text": "याची कल्पना करण सुद्धा आज कठीण आहे तसं",
    "start_time": 1206.96,
    "duration": 4.32
  },
  {
    "text": "चांगलं होत वाईट होत हा विषय वेगळा आहे पण",
    "start_time": 1209.36,
    "duration": 4.64
  },
  {
    "text": "ते वातावरण वेगळं होत एवढं नक्की तेव्हा",
    "start_time": 1211.28,
    "duration": 4.96
  },
  {
    "text": "त्या काळातल्या सरकारकडून तिथल्या अवकून",
    "start_time": 1214.0,
    "duration": 6.0
  },
  {
    "text": "झाला लगेच की तुमच्या इनामांची या",
    "start_time": 1216.24,
    "duration": 7.04
  },
  {
    "text": "सगळ्यांनी कागदपत्र हजर करा नाहीतर ती",
    "start_time": 1220.0,
    "duration": 7.52
  },
  {
    "text": "जप्त केली जातील आपल्याकडे होते सरकार जमा",
    "start_time": 1223.28,
    "duration": 6.56
  },
  {
    "text": "सरकार जमा होईल",
    "start_time": 1227.52,
    "duration": 5.36
  },
  {
    "text": "तेव्हा टाकल आमच्याकडे काय कागदपत्र वगैरे",
    "start_time": 1229.84,
    "duration": 5.76
  },
  {
    "text": "नाही ते भूर उतरत नाही तोपर्यंत दिसत नसत",
    "start_time": 1232.88,
    "duration": 4.0
  },
  {
    "text": "स्वच्छ",
    "start_time": 1235.6,
    "duration": 4.88
  },
  {
    "text": "तेव्हा सारा येतो ना डोळ्यावर तसं होत हा",
    "start_time": 1236.88,
    "duration": 5.919
  },
  {
    "text": "सारा आजही इनाम तारुण्याने येतो",
    "start_time": 1240.48,
    "duration": 4.8
  },
  {
    "text": "सौंदर्याने येतो पैशाने येतो पिढ्यात आला",
    "start_time": 1242.799,
    "duration": 5.521
  },
  {
    "text": "असला तर येतो खूप मार्गाने येतो आणि जर",
    "start_time": 1245.28,
    "duration": 5.2
  },
  {
    "text": "आपल्याला उद्धरून जायचं असेल तर कोणातरी",
    "start_time": 1248.32,
    "duration": 4.719
  },
  {
    "text": "सत्पुरुषाच्या पाया पडावेच खर बरोबर ते",
    "start_time": 1250.48,
    "duration": 5.36
  },
  {
    "text": "सगळ उतरवत होते आणि मग डोळे स्वच्छ होतात",
    "start_time": 1253.039,
    "duration": 5.361
  },
  {
    "text": "मग दिसतो भगवंत स्वच्छ डोळ्याने भगवंत",
    "start_time": 1255.84,
    "duration": 7.52
  },
  {
    "text": "दिसतो सुद्धा तर",
    "start_time": 1258.4,
    "duration": 7.44
  },
  {
    "text": "कळून टाकल आमच्याकडे काही कागदपत्र",
    "start_time": 1263.36,
    "duration": 6.559
  },
  {
    "text": "आम्ही वंश परंपरा हे इनाम आमच्याकडे आहे",
    "start_time": 1265.84,
    "duration": 6.959
  },
  {
    "text": "वंश परंपरा आहे ठीक आहे उत्तर आलं त्याच",
    "start_time": 1269.919,
    "duration": 5.361
  },
  {
    "text": "सरकार शेवटी सत्ता कोणाची हा प्रश्न आहे",
    "start_time": 1272.799,
    "duration": 5.601
  },
  {
    "text": "सत्तेन उत्तर दिलं त्याच की हे सगळं जप्त",
    "start_time": 1275.28,
    "duration": 5.92
  },
  {
    "text": "करायला ठरवलेल आहे त्याप्रमाणे",
    "start_time": 1278.4,
    "duration": 5.2
  },
  {
    "text": "बंद",
    "start_time": 1281.2,
    "duration": 4.88
  },
  {
    "text": "सगळे जे काही",
    "start_time": 1283.6,
    "duration": 4.64
  },
  {
    "text": "परंपरा चालत आला आहे ते सगळं जप्त",
    "start_time": 1286.08,
    "duration": 5.36
  },
  {
    "text": "केल्याचा हुकूम आला सत्ते पुढे काही नाही",
    "start_time": 1288.24,
    "duration": 8.319
  },
  {
    "text": "त्यामुळे गेल दिवशी पासून बंद जायला",
    "start_time": 1291.44,
    "duration": 5.119
  },
  {
    "text": "तेव्हा जरा उतरला थोड डोळ्यावर थोड दूर",
    "start_time": 1297.12,
    "duration": 6.88
  },
  {
    "text": "उतर आता काहीतरी केलं पाहिजे सरकारात जाऊन",
    "start_time": 1301.52,
    "duration": 5.76
  },
  {
    "text": "काय करणार तरी आधीच उत्तर देऊन टाकले तिथ",
    "start_time": 1304.0,
    "duration": 6.08
  },
  {
    "text": "मागून मागून काय उपयोग झाला नाही तेव्हा",
    "start_time": 1307.28,
    "duration": 5.84
  },
  {
    "text": "कळलं की आपल्याच या गावामध्ये सत्पुरुष",
    "start_time": 1310.08,
    "duration": 5.28
  },
  {
    "text": "आहेत स्वामींच्याकडे जाऊन काही मार्ग",
    "start_time": 1313.12,
    "duration": 5.12
  },
  {
    "text": "निघतो दुसरा काही मार्ग नाही राहिला गेली",
    "start_time": 1315.36,
    "duration": 5.679
  },
  {
    "text": "गेली सत्ता गेली की ज्याचं केवळ सत्तेवर",
    "start_time": 1318.24,
    "duration": 6.72
  },
  {
    "text": "चाललंय तो निर्बल होतो",
    "start_time": 1321.039,
    "duration": 5.601
  },
  {
    "text": "सत्तेवर चाललो नाही त्याला प्रश्न येत",
    "start_time": 1324.96,
    "duration": 3.68
  },
  {
    "text": "नाही आणि ईश्वरी सत्तेने चालणाऱ्याला कधीच",
    "start_time": 1326.64,
    "duration": 6.279
  },
  {
    "text": "प्रश्न येत नाही तर",
    "start_time": 1328.64,
    "duration": 4.279
  },
  {
    "text": "काकुळतीला येऊन यांच्याकडे गेले",
    "start_time": 1333.679,
    "duration": 4.961
  },
  {
    "text": "स्वामींच्याकडे म्हणाले असं असं झालेल आहे",
    "start_time": 1335.28,
    "duration": 6.96
  },
  {
    "text": "ते आम्ही तुम्हाला शरणा काही करा हे काय",
    "start_time": 1338.64,
    "duration": 6.64
  },
  {
    "text": "जे झाल ते काय निवारण करायचं",
    "start_time": 1342.24,
    "duration": 5.679
  },
  {
    "text": "स्वामी म्हणाले ज्यांनी हा हुकूम आपल्या",
    "start_time": 1345.28,
    "duration": 4.879
  },
  {
    "text": "मुलखातल्या अधिकाऱ्यांनी सोडला त्यांना",
    "start_time": 1347.919,
    "duration": 4.321
  },
  {
    "text": "घेऊन या",
    "start_time": 1350.159,
    "duration": 3.601
  },
  {
    "text": "त्यांच्या पाया पडले त्यांना घेऊन आले",
    "start_time": 1352.24,
    "duration": 3.919
  },
  {
    "text": "बाबा आम्ही एकदा या तरी आमचं गेलं ते गेलं",
    "start_time": 1353.76,
    "duration": 4.159
  },
  {
    "text": "पण त्यांच्याकडे तरी या आमच्याकडे काही",
    "start_time": 1356.159,
    "duration": 4.0
  },
  {
    "text": "दाखवायला काही नाही.",
    "start_time": 1357.919,
    "duration": 4.0
  },
  {
    "text": "ते आल्याबरोबर स्वामींनी त्यांच्या",
    "start_time": 1360.159,
    "duration": 5.52
  },
  {
    "text": "पद्धतीने एक दोन शिव्या त्यांना दिल्या.",
    "start_time": 1361.919,
    "duration": 5.521
  },
  {
    "text": "म्हटले महापुरुषांच काम वेगवेगळ्या",
    "start_time": 1365.679,
    "duration": 3.36
  },
  {
    "text": "प्रकारचा",
    "start_time": 1367.44,
    "duration": 4.8
  },
  {
    "text": "आणि मग म्हणाले की तुम्हाला त्याचा मिळत",
    "start_time": 1369.039,
    "duration": 5.12
  },
  {
    "text": "नाही ना काही कागदपत्र पुरावा नाहीये ना",
    "start_time": 1372.24,
    "duration": 4.0
  },
  {
    "text": "कसं असेल",
    "start_time": 1374.159,
    "duration": 6.4
  },
  {
    "text": "समोरच्या नदीत दगड बाहेर काढा म्हणले दगड",
    "start_time": 1376.24,
    "duration": 7.28
  },
  {
    "text": "आपल्याला माहित खरोखर या सगळ्या मंडळींनी",
    "start_time": 1380.559,
    "duration": 6.081
  },
  {
    "text": "धडपड केली आणि नदीमध्ये गाळामध्ये रतलेले",
    "start_time": 1383.52,
    "duration": 6.0
  },
  {
    "text": "ती शाळा काढली शाळा सापडली मोठी",
    "start_time": 1386.64,
    "duration": 6.0
  },
  {
    "text": "त्याच्यावर यांचे मूळ पुरुष कोण त्यांना",
    "start_time": 1389.52,
    "duration": 6.399
  },
  {
    "text": "हे नाम का दिलं कोणत्या त्या तारखेला दिलं",
    "start_time": 1392.64,
    "duration": 7.44
  },
  {
    "text": "त्यावेळच तिथी नोंद देणारा माणूस त्याची",
    "start_time": 1395.919,
    "duration": 8.161
  },
  {
    "text": "नोंद सगळं त्या शिळ आणून समोर ठेवल्यावर",
    "start_time": 1400.08,
    "duration": 5.92
  },
  {
    "text": "हुकूम मागे",
    "start_time": 1404.08,
    "duration": 7.92
  },
  {
    "text": "म्हणाले आता जे कामासाठी दिलं ते काम करा",
    "start_time": 1406.0,
    "duration": 7.679
  },
  {
    "text": "तेव्हा",
    "start_time": 1412.0,
    "duration": 6.559
  },
  {
    "text": "आपण अशा तर लक्षात ठेवाव हे सगळं कशाचही",
    "start_time": 1413.679,
    "duration": 8.0
  },
  {
    "text": "परमार्थातली ही धोंड आहे",
    "start_time": 1418.559,
    "duration": 6.0
  },
  {
    "text": "बाजूला करायची केल्याशिवाय",
    "start_time": 1421.679,
    "duration": 7.161
  },
  {
    "text": "भगवंताचे दर्शन आहे",
    "start_time": 1424.559,
    "duration": 4.281
  },
  {
    "text": "त्यांच्याकडे एक असतं सूचकताही असते",
    "start_time": 1429.28,
    "duration": 7.68
  },
  {
    "text": "परीक्षाही असते अशा महापुरुषांचे कडे अनेक",
    "start_time": 1432.64,
    "duration": 6.56
  },
  {
    "text": "गोष्टी असतात",
    "start_time": 1436.96,
    "duration": 6.24
  },
  {
    "text": "जसं त्यांच्या चरित्रात आपल्याला",
    "start_time": 1439.2,
    "duration": 7.12
  },
  {
    "text": "दोन्ही गोष्टी झालेल्या आढळतात",
    "start_time": 1443.2,
    "duration": 6.12
  },
  {
    "text": "एक",
    "start_time": 1446.32,
    "duration": 3.0
  },
  {
    "text": "सिंधुबंध आपल्या",
    "start_time": 1450.96,
    "duration": 3.599
  },
  {
    "text": "की",
    "start_time": 1454.96,
    "duration": 3.0
  },
  {
    "text": "सोलापूरच्या",
    "start_time": 1458.159,
    "duration": 4.561
  },
  {
    "text": "मुक्कामी स्वामी असताना दत्त मंदिरामध्ये",
    "start_time": 1459.679,
    "duration": 6.801
  },
  {
    "text": "बसत असतात प्रदक्षिणेच्या मार्गावर",
    "start_time": 1462.72,
    "duration": 5.6
  },
  {
    "text": "चिंत म्हणतात प्रदक्षणा घालत असताना",
    "start_time": 1466.48,
    "duration": 5.28
  },
  {
    "text": "त्यांच्या समोरून गेले हा पुरुष तेजस्वी",
    "start_time": 1468.32,
    "duration": 6.0
  },
  {
    "text": "लक्षात बाकीच काही कळलं नाही कोणीतरी",
    "start_time": 1471.76,
    "duration": 5.2
  },
  {
    "text": "आवलेले आहेत",
    "start_time": 1474.32,
    "duration": 5.76
  },
  {
    "text": "तेव्हा म्हणाले",
    "start_time": 1476.96,
    "duration": 6.16
  },
  {
    "text": "जाता आला पण प्रदक्षिणा आपल्या प्रदक्षणा",
    "start_time": 1480.08,
    "duration": 6.16
  },
  {
    "text": "कशा असतात ते पण माहितीच आपल्या",
    "start_time": 1483.12,
    "duration": 5.36
  },
  {
    "text": "सगळ्या संबंध असतोच सत्पुरुष जरी",
    "start_time": 1486.24,
    "duration": 4.0
  },
  {
    "text": "वेगवेगळ्या मार्गाने काम करत असले तरी काम",
    "start_time": 1488.48,
    "duration": 6.0
  },
  {
    "text": "ते चालूच असत तेव्हा प्रदक्षिणा दत्ताला",
    "start_time": 1490.24,
    "duration": 7.039
  },
  {
    "text": "वाटेत बसलेल्या माणसाकडे लक्ष गेलं वेदल",
    "start_time": 1494.48,
    "duration": 6.319
  },
  {
    "text": "गेलं तेव्हा मनात आलं कोणीतरी सिद्ध पुरुष",
    "start_time": 1497.279,
    "duration": 5.841
  },
  {
    "text": "असेल",
    "start_time": 1500.799,
    "duration": 4.801
  },
  {
    "text": "असावा",
    "start_time": 1503.12,
    "duration": 4.72
  },
  {
    "text": "अस म्हणत म्हणत प्रदक्षिणा पूर्ण केली",
    "start_time": 1505.6,
    "duration": 4.0
  },
  {
    "text": "पुन्हा जेव्हा प्रदक्षिणेच्या वेळेला",
    "start_time": 1507.84,
    "duration": 4.64
  },
  {
    "text": "तिथून समोरून गेले तेव्हा स्वामी म्हणाले",
    "start_time": 1509.6,
    "duration": 4.72
  },
  {
    "text": "आम्ही सिद्ध पुरुष असो नाहीतर कोणी असो",
    "start_time": 1512.48,
    "duration": 4.96
  },
  {
    "text": "तुम्ही प्रदक्ष",
    "start_time": 1514.32,
    "duration": 5.2
  },
  {
    "text": "पाहिजेत",
    "start_time": 1517.44,
    "duration": 7.04
  },
  {
    "text": "बोलून बोध करून वाटत नाही पटकन होत",
    "start_time": 1519.52,
    "duration": 7.2
  },
  {
    "text": "सपापून पुढे गेले आपली प्रदक्षणा सोडून",
    "start_time": 1524.48,
    "duration": 5.04
  },
  {
    "text": "आपण काहीतरी उद्योग केला मनात आल पण",
    "start_time": 1526.72,
    "duration": 5.36
  },
  {
    "text": "प्रदक्षणा पुढे येईपर्यंत दत्तगुरूंच",
    "start_time": 1529.52,
    "duration": 5.519
  },
  {
    "text": "स्मरण करण्याऐवजी हे स्मरण होत होत ना",
    "start_time": 1532.08,
    "duration": 5.52
  },
  {
    "text": "यांच्या डोक्यात कस आलं",
    "start_time": 1535.039,
    "duration": 5.841
  },
  {
    "text": "कदाचित मनकवडा मनुष्य कोणीतरी महापुरुष",
    "start_time": 1537.6,
    "duration": 6.24
  },
  {
    "text": "दुसरं डोक्यात आलं ना",
    "start_time": 1540.88,
    "duration": 6.32
  },
  {
    "text": "पुन्हा जवळून गेले प्रदक्षिणेच्या वेळेला",
    "start_time": 1543.84,
    "duration": 7.52
  },
  {
    "text": "आम्ही मनकवडे असून येतो आणि कोणी",
    "start_time": 1547.2,
    "duration": 8.079
  },
  {
    "text": "इतक सरळ बोलले नशीब म्हणायचं प्रदक्षिणा",
    "start_time": 1551.36,
    "duration": 6.64
  },
  {
    "text": "पाय धरले म्हणले",
    "start_time": 1555.279,
    "duration": 6.481
  },
  {
    "text": "तुम्ही कोण असाल ते असा घरी यांना घेऊन",
    "start_time": 1558.0,
    "duration": 7.12
  },
  {
    "text": "गेले घरी त्यांच्या घरी राहिले",
    "start_time": 1561.76,
    "duration": 6.32
  },
  {
    "text": "त्यांच्या मुलगाही श्रद्धावन श्रद्धावान",
    "start_time": 1565.12,
    "duration": 7.6
  },
  {
    "text": "अत्यंत त्यांच्यापेक्षाही कणभर कसं म्हणा",
    "start_time": 1568.08,
    "duration": 6.24
  },
  {
    "text": "तेव्हा",
    "start_time": 1572.72,
    "duration": 4.48
  },
  {
    "text": "मुलगा नोकरीला होता लहान होता नोकरीत होता",
    "start_time": 1574.32,
    "duration": 6.479
  },
  {
    "text": "कचेरीत आणि ही त्या काळची कलेक्टर कचेरी",
    "start_time": 1577.2,
    "duration": 7.359
  },
  {
    "text": "होती या काळात असे पण कलेक्टर आतमध्ये आले",
    "start_time": 1580.799,
    "duration": 7.681
  },
  {
    "text": "तर अत्यंत शिस्त असते आणि असेही काळ",
    "start_time": 1584.559,
    "duration": 8.24
  },
  {
    "text": "येत होत त्या काळात ते इंग्रजी शिस्त होती",
    "start_time": 1588.48,
    "duration": 6.72
  },
  {
    "text": "तेव्हा",
    "start_time": 1592.799,
    "duration": 6.721
  },
  {
    "text": "दहा लाजेरी लागलीच पाहिजे काही झाल तरी",
    "start_time": 1595.2,
    "duration": 7.2
  },
  {
    "text": "नाहीतर काय नोकरी सुद्धा गमवा लागायची वेळ",
    "start_time": 1599.52,
    "duration": 6.399
  },
  {
    "text": "तो कचेरीत होता दुसऱ्या दिवशी",
    "start_time": 1602.4,
    "duration": 5.759
  },
  {
    "text": "त्यांच्याकडे एक दिवशी असताना जेवायच्या",
    "start_time": 1605.919,
    "duration": 5.841
  },
  {
    "text": "वेळेला त्यांना आमंत्रण अस जेवायला येत",
    "start_time": 1608.159,
    "duration": 6.64
  },
  {
    "text": "जेवीत आणि जात",
    "start_time": 1611.76,
    "duration": 5.2
  },
  {
    "text": "जेवायला आले असताना त्यांच्या घरातल्या",
    "start_time": 1614.799,
    "duration": 5.36
  },
  {
    "text": "मंडळींच जरा एकमेकांच्या नेहमीची मंडळी",
    "start_time": 1616.96,
    "duration": 6.64
  },
  {
    "text": "होती त्याच्यातले त्यांना असं वाटत की हा",
    "start_time": 1620.159,
    "duration": 6.241
  },
  {
    "text": "पुरुष कुठे राहतो कसे बसतात राहतात काय",
    "start_time": 1623.6,
    "duration": 5.52
  },
  {
    "text": "काय कुणास पहिलं काय यांचा इतिहास माहित",
    "start_time": 1626.4,
    "duration": 4.8
  },
  {
    "text": "नाही कशात त्यातला कुठला काय माहिती नाही",
    "start_time": 1629.12,
    "duration": 4.4
  },
  {
    "text": "100 वर्ष 1श वर्षापूर्वीच्या काळाची गोष्ट",
    "start_time": 1631.2,
    "duration": 4.88
  },
  {
    "text": "आहे तर त्या काळात विचार केला तर असेच",
    "start_time": 1633.52,
    "duration": 5.44
  },
  {
    "text": "कशाला आपण हे करावं गळ्यात उघडून घ्यावं",
    "start_time": 1636.08,
    "duration": 5.839
  },
  {
    "text": "जेवायला घालाव त्याला बसवाव",
    "start_time": 1638.96,
    "duration": 8.079
  },
  {
    "text": "असं मनात आलं त्या दिवशी आले बसले",
    "start_time": 1641.919,
    "duration": 10.081
  },
  {
    "text": "म्हणले विक्षेप आहे आज आज काय आमच्याकडून",
    "start_time": 1647.039,
    "duration": 7.681
  },
  {
    "text": "अन्न ग्रहण होणार नाही",
    "start_time": 1652.0,
    "duration": 6.24
  },
  {
    "text": "निघाले निघून जेवणार नाही त्याप्रमाणे",
    "start_time": 1654.72,
    "duration": 4.959
  },
  {
    "text": "जेवले",
    "start_time": 1658.24,
    "duration": 3.76
  },
  {
    "text": "निघून गेले",
    "start_time": 1659.679,
    "duration": 4.48
  },
  {
    "text": "तेव्हा नाही लागलं म्हणाला आपण असा विचार",
    "start_time": 1662.0,
    "duration": 5.84
  },
  {
    "text": "केला चुकलं दुसऱ्या दिवशी आली जेवायची",
    "start_time": 1664.159,
    "duration": 7.361
  },
  {
    "text": "काही भाषा नाही जेवण तयार आहे भाषा नाही",
    "start_time": 1667.84,
    "duration": 6.959
  },
  {
    "text": "मुलाला वाटलं की हे चुकलेल आहे आपण",
    "start_time": 1671.52,
    "duration": 7.759
  },
  {
    "text": "दुरुस्त केल पाहिजे सुधारल पाहिजे म्हणून",
    "start_time": 1674.799,
    "duration": 8.0
  },
  {
    "text": "इकडे दहा च्या कचेरीची गडबड जिवंत लवकर",
    "start_time": 1679.279,
    "duration": 9.28
  },
  {
    "text": "जायचं होत तिकडे अडचण आहे नोकरीची अडचण",
    "start_time": 1682.799,
    "duration": 8.321
  },
  {
    "text": "आपल्या हातातली नाही",
    "start_time": 1688.559,
    "duration": 5.441
  },
  {
    "text": "तळक्याची नोकरी आहे",
    "start_time": 1691.12,
    "duration": 6.64
  },
  {
    "text": "त्यानी एक ठरवलं जहे महापुरुषच आहेत आणि",
    "start_time": 1694.0,
    "duration": 6.08
  },
  {
    "text": "जर जेवण घेत नाहीत तर जेवल्याशिवाय आपण",
    "start_time": 1697.76,
    "duration": 7.44
  },
  {
    "text": "जेवायचे नाही काय होईल",
    "start_time": 1700.08,
    "duration": 8.959
  },
  {
    "text": "की कुणाला देतात परीक्षा पाहतात सांगितलं",
    "start_time": 1705.2,
    "duration": 10.479
  },
  {
    "text": "ना तसं सूचके सूचकता ही असते तेव्हा",
    "start_time": 1709.039,
    "duration": 9.36
  },
  {
    "text": "हा बसून राहिला स्वामी",
    "start_time": 1715.679,
    "duration": 6.72
  },
  {
    "text": "काय असेल ते जेवण कराव अशी इच्छा",
    "start_time": 1718.399,
    "duration": 5.76
  },
  {
    "text": "काही बोलले नाही 11 वाजेपर्यंत बसून",
    "start_time": 1722.399,
    "duration": 5.28
  },
  {
    "text": "राहिलेची कचरीची वेळ टळली चांगली टळू दिली",
    "start_time": 1724.159,
    "duration": 6.52
  },
  {
    "text": "व्यवस्थित",
    "start_time": 1727.679,
    "duration": 3.0
  },
  {
    "text": "आणि मग गेल्यावर पटकन जेवला अरा वाजता",
    "start_time": 1732.08,
    "duration": 6.88
  },
  {
    "text": "गेला मला आज आता काय होईल ते होईल कदाचित",
    "start_time": 1736.159,
    "duration": 5.52
  },
  {
    "text": "घैरे जरी लागेल त्याचा काही विशेष नाही पण",
    "start_time": 1738.96,
    "duration": 5.68
  },
  {
    "text": "नोकरी गेली तरी तयारी ठेवावी लागेल पण",
    "start_time": 1741.679,
    "duration": 5.6
  },
  {
    "text": "शेवटी एक महापुरुष आहे आणि",
    "start_time": 1744.64,
    "duration": 5.759
  },
  {
    "text": "त्याच्या सेवे मध्ये झालं एवढं तरी होईल",
    "start_time": 1747.279,
    "duration": 7.161
  },
  {
    "text": "निदान अनेकदा",
    "start_time": 1750.399,
    "duration": 4.041
  },
  {
    "text": "आठवण झाली एका माणसाची",
    "start_time": 1757.279,
    "duration": 5.601
  },
  {
    "text": "वयस्कर होते",
    "start_time": 1759.679,
    "duration": 5.041
  },
  {
    "text": "सगळं आयुष्य गेल असं गेलं तसं गेलं चाललं",
    "start_time": 1762.88,
    "duration": 5.679
  },
  {
    "text": "होत चर्चा जाऊ दे कस आयुष्य आता तुम्ही",
    "start_time": 1764.72,
    "duration": 6.48
  },
  {
    "text": "आले मनात तुमच्या चांगलं काहीतरी व्हाव",
    "start_time": 1768.559,
    "duration": 5.761
  },
  {
    "text": "असं वाटतंय ना आल आता ठीक आहे आपलं आलं",
    "start_time": 1771.2,
    "duration": 6.16
  },
  {
    "text": "जवळ हरकत",
    "start_time": 1774.32,
    "duration": 8.0
  },
  {
    "text": "आता जायचंच आहे तर असं काही जाऊ नका जा",
    "start_time": 1777.36,
    "duration": 8.16
  },
  {
    "text": "घ्या महाराजांचे",
    "start_time": 1782.32,
    "duration": 5.52
  },
  {
    "text": "संध्याकाळी गेल तरी काळजी करू नका जाताना",
    "start_time": 1785.52,
    "duration": 6.32
  },
  {
    "text": "महाराजांची म्हणून जा एवढ सुद्धा खूप होईल",
    "start_time": 1787.84,
    "duration": 6.319
  },
  {
    "text": "त्यांची आठवण झाली म्हणून मी उल्लेख केला",
    "start_time": 1791.84,
    "duration": 6.88
  },
  {
    "text": "आता तेव्हा हे",
    "start_time": 1794.159,
    "duration": 8.561
  },
  {
    "text": "मुलाचं झालं गेला एक काम आहे आपलं शेवटी",
    "start_time": 1798.72,
    "duration": 7.199
  },
  {
    "text": "आपली चूक झालेली आहे कचेरीची चूक आहे कच",
    "start_time": 1802.72,
    "duration": 4.959
  },
  {
    "text": "हेड क्लार्कडे जाऊन क्षमा मागितली पाहिजे",
    "start_time": 1805.919,
    "duration": 4.801
  },
  {
    "text": "त्याप्रमाणे आणि काय होत असेल तर बदली",
    "start_time": 1807.679,
    "duration": 6.24
  },
  {
    "text": "करायची नसेल तर आपलं सरळ निघणे दुस काही",
    "start_time": 1810.72,
    "duration": 4.72
  },
  {
    "text": "नाही",
    "start_time": 1813.919,
    "duration": 4.081
  },
  {
    "text": "गेले त्यांची त्या काळातले हेडला ते",
    "start_time": 1815.44,
    "duration": 5.52
  },
  {
    "text": "म्हणाले तुम्ही आज म्हणले आमच्या आधी झाला",
    "start_time": 1818.0,
    "duration": 5.96
  },
  {
    "text": "म्हणले",
    "start_time": 1820.96,
    "duration": 3.0
  },
  {
    "text": "काही बोललेच नाही",
    "start_time": 1824.24,
    "duration": 7.12
  },
  {
    "text": "कामात होतो तुमची मलेरी",
    "start_time": 1827.36,
    "duration": 7.919
  },
  {
    "text": "पुस्तकात त्यांची हजेरी माळली",
    "start_time": 1831.36,
    "duration": 3.919
  },
  {
    "text": "तेव्हा",
    "start_time": 1836.24,
    "duration": 4.48
  },
  {
    "text": "असे कुणाला द्यायची सामर्थ्य त्यांच्याकडे",
    "start_time": 1838.08,
    "duration": 4.63
  },
  {
    "text": "आहे",
    "start_time": 1840.72,
    "duration": 5.099
  },
  {
    "text": "[संगीत]",
    "start_time": 1842.71,
    "duration": 3.109
  },
  {
    "text": "ज्या अक्कलकोटला त्यांचे हे सगळं जवळजवळ",
    "start_time": 1853.44,
    "duration": 8.64
  },
  {
    "text": "20 21 वर्षांच शेवटचं वास्तव्य इथे केलं",
    "start_time": 1857.44,
    "duration": 4.64
  },
  {
    "text": "तिथे त्यांना खरं पहिल्यांदा या",
    "start_time": 1862.96,
    "duration": 7.04
  },
  {
    "text": "चिंतुवंतांनी न्यायचा प्रयत्न केला",
    "start_time": 1865.12,
    "duration": 6.96
  },
  {
    "text": "तर त्यावेळेला",
    "start_time": 1870.0,
    "duration": 7.919
  },
  {
    "text": "उन्हाळ्याचे दिवस होते आणि प्रार्थना केली",
    "start_time": 1872.08,
    "duration": 9.04
  },
  {
    "text": "सोलापूरून त्यांची कारभारी म्हणून नेमणूक",
    "start_time": 1877.919,
    "duration": 5.601
  },
  {
    "text": "अक्कलकोटला होते",
    "start_time": 1881.12,
    "duration": 3.919
  },
  {
    "text": "तेव्हा जाताना तुम्ही माझ्याबरोबर",
    "start_time": 1883.52,
    "duration": 3.6
  },
  {
    "text": "अक्कलकोटला चला म्हणून स्वामींना",
    "start_time": 1885.039,
    "duration": 6.24
  },
  {
    "text": "प्रार्थना केली होती स्वामी म्हटले तुम्ही",
    "start_time": 1887.12,
    "duration": 4.159
  },
  {
    "text": "सध्या उन्हाळा फार आहे म्हणले ध्यानात",
    "start_time": 1891.6,
    "duration": 5.199
  },
  {
    "text": "कसला आला उन्हाळा काय दोन वाजता दुपार",
    "start_time": 1894.64,
    "duration": 5.12
  },
  {
    "text": "येणार आहे उन्हाळा फार आहे काय होतं",
    "start_time": 1896.799,
    "duration": 5.921
  },
  {
    "text": "सूचकता त्यातली कळत नाहीती नंतर कळली",
    "start_time": 1899.76,
    "duration": 5.6
  },
  {
    "text": "उन्हाळा फार आहे त्या काळात तिथे जे राजे",
    "start_time": 1902.72,
    "duration": 4.24
  },
  {
    "text": "होते",
    "start_time": 1905.36,
    "duration": 3.919
  },
  {
    "text": "तेवढे श्रद्धा",
    "start_time": 1906.96,
    "duration": 4.88
  },
  {
    "text": "बारीक हो उन्हाळा फार आहे म्हणले पुढे",
    "start_time": 1909.279,
    "duration": 6.0
  },
  {
    "text": "पावसाळा येईल त्यावेळेला येऊ",
    "start_time": 1911.84,
    "duration": 6.16
  },
  {
    "text": "आता कुठला पावसाळा पावसाळा टाळायची वेळ",
    "start_time": 1915.279,
    "duration": 4.321
  },
  {
    "text": "आली होती",
    "start_time": 1918.0,
    "duration": 3.519
  },
  {
    "text": "हा उन्हाळा एवढा लांबला आपल्याला माहिती",
    "start_time": 1919.6,
    "duration": 4.079
  },
  {
    "text": "अनेकदा ओढ देतो पावसा आपण म्हणतो तशी त्या",
    "start_time": 1921.519,
    "duration": 4.561
  },
  {
    "text": "काळा वर्षी ओढ दिलेली होती पावसाने हे जे",
    "start_time": 1923.679,
    "duration": 4.321
  },
  {
    "text": "आपले नेहमीचे जून जुलै ऑगस्ट महिने असतात",
    "start_time": 1926.08,
    "duration": 6.8
  },
  {
    "text": "ते सगळे गेले आणि नेहमीचे सगळे पावसाचे",
    "start_time": 1928.0,
    "duration": 7.84
  },
  {
    "text": "महिने गेले हे काही तिकडे गेले नाही",
    "start_time": 1932.88,
    "duration": 5.919
  },
  {
    "text": "दरम्यान ते जे राजे होते त्या काळातले",
    "start_time": 1935.84,
    "duration": 6.8
  },
  {
    "text": "मालोजीराजांचे वडील तेव्हा त्यांची",
    "start_time": 1938.799,
    "duration": 6.88
  },
  {
    "text": "प्रकृती ढासळली आणि ते गेले आणि नंतर",
    "start_time": 1942.64,
    "duration": 6.24
  },
  {
    "text": "स्वामी महाराज आता",
    "start_time": 1945.679,
    "duration": 5.041
  },
  {
    "text": "मालाजी राजांची पहिल्यापासून",
    "start_time": 1948.88,
    "duration": 3.6
  },
  {
    "text": "दत्तगुरूंच्यावर श्रद्धा होती आणि",
    "start_time": 1950.72,
    "duration": 5.12
  },
  {
    "text": "गाणगापूरला जाती",
    "start_time": 1952.48,
    "duration": 6.4
  },
  {
    "text": "हे गेले आणि",
    "start_time": 1955.84,
    "duration": 5.52
  },
  {
    "text": "त्या वेळेला पावसाळ्याची सगळी ओड देऊन",
    "start_time": 1958.88,
    "duration": 5.519
  },
  {
    "text": "सगळी पावसाळ्याची नक्षत्र संपली आणि",
    "start_time": 1961.36,
    "duration": 5.199
  },
  {
    "text": "गेल्यानंतर जो पाऊस सुरू झाला",
    "start_time": 1964.399,
    "duration": 4.241
  },
  {
    "text": "कार्तिकामध्ये",
    "start_time": 1966.559,
    "duration": 5.041
  },
  {
    "text": "तो उत्तम झाला आणि कार्तिकानंतरची",
    "start_time": 1968.64,
    "duration": 5.84
  },
  {
    "text": "नंतर सगळी पिक आली",
    "start_time": 1971.6,
    "duration": 5.679
  },
  {
    "text": "शेकलकोटची स्वतःची परिस्थिती पहिल्यांदा",
    "start_time": 1974.48,
    "duration": 5.679
  },
  {
    "text": "केली तेव्हाची तिथून जे गेले ते राजांच्या",
    "start_time": 1977.279,
    "duration": 5.52
  },
  {
    "text": "संबंधामुळे तिथेच राहिले राजांचा संबंध",
    "start_time": 1980.159,
    "duration": 6.721
  },
  {
    "text": "सुद्धा का आला तर राजे त्याच वर्षी ते",
    "start_time": 1982.799,
    "duration": 6.801
  },
  {
    "text": "राज्यावर बसले त्यानंतर ते गणगापूरला",
    "start_time": 1986.88,
    "duration": 5.919
  },
  {
    "text": "त्यांच्या श्रद्धेप्रमाणे गेले तिथे सगळं",
    "start_time": 1989.6,
    "duration": 5.679
  },
  {
    "text": "नेहमीप्रमाणे काय त्यांचे जे असतात",
    "start_time": 1992.799,
    "duration": 7.76
  },
  {
    "text": "त्याप्रमाणे केले आणि ते सगळं करून ला आले",
    "start_time": 1995.279,
    "duration": 9.201
  },
  {
    "text": "अक्कलकोटला परत आले ते म्हणले होते ना",
    "start_time": 2000.559,
    "duration": 6.161
  },
  {
    "text": "उन्हाळा आहे पावसाळा आल्यावर",
    "start_time": 2004.48,
    "duration": 5.439
  },
  {
    "text": "त्याप्रमाणे आले होते",
    "start_time": 2006.72,
    "duration": 5.28
  },
  {
    "text": "आणि हे मात्र गाणगापूरला जाऊन आले",
    "start_time": 2009.919,
    "duration": 4.081
  },
  {
    "text": "त्यांच्या श्रद्धेप्रमाणे",
    "start_time": 2012.0,
    "duration": 4.08
  },
  {
    "text": "आणि त्या दिवशी रात्री परत आल्यावर",
    "start_time": 2014.0,
    "duration": 4.799
  },
  {
    "text": "राजांना स्वप्न पडलं",
    "start_time": 2016.08,
    "duration": 4.719
  },
  {
    "text": "स्वप्नामध्ये नरसिंह सरस्वती आले ते",
    "start_time": 2018.799,
    "duration": 4.48
  },
  {
    "text": "त्यांच ठिकाण",
    "start_time": 2020.799,
    "duration": 4.801
  },
  {
    "text": "नरसिंह सरस्वती आले आणि त्यांनी सांगितलं",
    "start_time": 2023.279,
    "duration": 4.561
  },
  {
    "text": "मी तुझ्या गावी राहायला आलो आणि तू कशाला",
    "start_time": 2025.6,
    "duration": 5.04
  },
  {
    "text": "गणगास",
    "start_time": 2027.84,
    "duration": 5.28
  },
  {
    "text": "त्यांना कळलं विभवती कोण आहे आणि कशासाठी",
    "start_time": 2030.64,
    "duration": 4.639
  },
  {
    "text": "आली",
    "start_time": 2033.12,
    "duration": 2.159
  },
  {
    "text": "महाराजांनी म्हणले त्याची आठवण झाली",
    "start_time": 2036.96,
    "duration": 5.04
  },
  {
    "text": "त्याच्याशी संबंधित आहे ते सांगतो",
    "start_time": 2038.799,
    "duration": 7.281
  },
  {
    "text": "की ओळख त्यांची कशी देतात किंवा काय असतं",
    "start_time": 2042.0,
    "duration": 8.079
  },
  {
    "text": "आणि त्यांना काय सुचाव लागत",
    "start_time": 2046.08,
    "duration": 9.12
  },
  {
    "text": "त्या वटवृक्षाखाली बसलेल्या असताना",
    "start_time": 2050.079,
    "duration": 7.84
  },
  {
    "text": "कृद्ध होते रागाले होते कोणाला जवळ येऊ",
    "start_time": 2055.2,
    "duration": 4.959
  },
  {
    "text": "दिल नाही काही नाही",
    "start_time": 2057.919,
    "duration": 5.521
  },
  {
    "text": "तर त्या सगळ्या भेटायला आलेल्या",
    "start_time": 2060.159,
    "duration": 5.68
  },
  {
    "text": "पाया पडायला आलेल्या",
    "start_time": 2063.44,
    "duration": 6.639
  },
  {
    "text": "माणसामध्ये एक अश्रद्ध माणूस होता तो",
    "start_time": 2065.839,
    "duration": 6.56
  },
  {
    "text": "दुसऱ्याला काय म्हणाला",
    "start_time": 2070.079,
    "duration": 6.08
  },
  {
    "text": "साधु पुरुष एवढा राग कसा",
    "start_time": 2072.399,
    "duration": 6.561
  },
  {
    "text": "आपण रागाची काही सन दिली",
    "start_time": 2076.159,
    "duration": 7.041
  },
  {
    "text": "सत्पुरुषांच्याकडे नाही काय पण अश्रद्धा",
    "start_time": 2078.96,
    "duration": 6.639
  },
  {
    "text": "असल्यामुळे मुळातच आधी हा प्रश्न होता",
    "start_time": 2083.2,
    "duration": 5.439
  },
  {
    "text": "त्यामुळे मग पुढचे प्रश्न होतात निर्माण",
    "start_time": 2085.599,
    "duration": 6.48
  },
  {
    "text": "साधू यांना राग कसा",
    "start_time": 2088.639,
    "duration": 6.24
  },
  {
    "text": "बाजूला ला असंख्य लोक बसलेले असताना",
    "start_time": 2092.079,
    "duration": 4.401
  },
  {
    "text": "त्यानंतर",
    "start_time": 2094.879,
    "duration": 5.601
  },
  {
    "text": "एक दिवशी सगळ्यांसमोर मोठ्याने म्हणाले",
    "start_time": 2096.48,
    "duration": 6.879
  },
  {
    "text": "मला जर राग असता इथे जेवढे लोक बसलेत",
    "start_time": 2100.48,
    "duration": 5.84
  },
  {
    "text": "तेवढ्यांची भाजी झाली असती म्हणले",
    "start_time": 2103.359,
    "duration": 5.601
  },
  {
    "text": "भाजी करून खायला गेली असती म्हणले राग जर",
    "start_time": 2106.32,
    "duration": 4.56
  },
  {
    "text": "असता तर",
    "start_time": 2108.96,
    "duration": 5.68
  },
  {
    "text": "तो नाही म्हणून हे चालल सगळ्यांची नाहीतर",
    "start_time": 2110.88,
    "duration": 5.6
  },
  {
    "text": "शक्यच नाही म्हणले भाजी करून महाराज",
    "start_time": 2114.64,
    "duration": 4.16
  },
  {
    "text": "म्हणले महाराजांना एकदा आम्ही एवढे अपराध",
    "start_time": 2116.48,
    "duration": 5.04
  },
  {
    "text": "करतो आपण शिक्षका करत नाही महाराज म्हणले",
    "start_time": 2118.8,
    "duration": 4.64
  },
  {
    "text": "तुम्ही जे अपराध करता त्याच्या शिक्षा करत",
    "start_time": 2121.52,
    "duration": 4.559
  },
  {
    "text": "बसलो तर तुमच तुम्हाला दिवस पुरायचं नाही",
    "start_time": 2123.44,
    "duration": 5.679
  },
  {
    "text": "मला आयुष्य पुरायचं नाही",
    "start_time": 2126.079,
    "duration": 6.0
  },
  {
    "text": "अशी अवस्था आहे खर आहे ते आपण आपल्या",
    "start_time": 2129.119,
    "duration": 5.281
  },
  {
    "text": "पुरता विचार करून बघावा त्यांना अपेक्षित",
    "start_time": 2132.079,
    "duration": 4.721
  },
  {
    "text": "काय नाही आम्ही काय जगतोय असा विचार केला",
    "start_time": 2134.4,
    "duration": 5.04
  },
  {
    "text": "तर ते जर प्रत्येक आमच्या गुन्हाला जर",
    "start_time": 2136.8,
    "duration": 6.88
  },
  {
    "text": "शिक्षा करायला बसले तर झेपणार नाही ते",
    "start_time": 2139.44,
    "duration": 8.639
  },
  {
    "text": "क्षमाशील असतात आणि आशेवर असतात हे",
    "start_time": 2143.68,
    "duration": 7.679
  },
  {
    "text": "सुधारेल होईल हेच खरं ते त्यांनी रागाच्या",
    "start_time": 2148.079,
    "duration": 4.241
  },
  {
    "text": "भाषेत सांगितलं",
    "start_time": 2151.359,
    "duration": 4.321
  },
  {
    "text": "त्यामुळे लक्षात राहिल आता",
    "start_time": 2152.32,
    "duration": 6.24
  },
  {
    "text": "शेवट फक्त आपल्या संबंधित एकच आठवण सांगतो",
    "start_time": 2155.68,
    "duration": 4.88
  },
  {
    "text": "फक्त थांबतो सगळ आपल्या माहितीच स्मरण",
    "start_time": 2158.56,
    "duration": 7.08
  },
  {
    "text": "कराव फक्त एवढी इच्छा तर",
    "start_time": 2160.56,
    "duration": 5.08
  },
  {
    "text": "संन्यासी माणूस त्या हिमालयाच्या",
    "start_time": 2166.56,
    "duration": 5.6
  },
  {
    "text": "पायथ्याशी तपश्चला बसला होता दत्त दर्शन",
    "start_time": 2168.96,
    "duration": 5.68
  },
  {
    "text": "व्हाव म्हणून निरंजन स्वामींनी सगळ्यांना",
    "start_time": 2172.16,
    "duration": 5.28
  },
  {
    "text": "पाय दिले बर का बरोबर प्रत्येक जण त्याची",
    "start_time": 2174.64,
    "duration": 5.439
  },
  {
    "text": "पुण्यतिथी आहे त्यांची पुण्यतिथी सुधी",
    "start_time": 2177.44,
    "duration": 4.32
  },
  {
    "text": "गेल्या वेळेला शनिवारी",
    "start_time": 2180.079,
    "duration": 4.241
  },
  {
    "text": "आज जयंतीचा दिवस आहे त्यांचे तेच",
    "start_time": 2181.76,
    "duration": 4.16
  },
  {
    "text": "एकमेकांना त्यांनी बाय देऊन टाकले",
    "start_time": 2184.32,
    "duration": 4.96
  },
  {
    "text": "त्यामुळे स्वामी निरंजन स्वामींची कृपा",
    "start_time": 2185.92,
    "duration": 6.08
  },
  {
    "text": "आहे निरंजन स्मरण आता आपल शनिवारी सुरू",
    "start_time": 2189.28,
    "duration": 4.96
  },
  {
    "text": "आहे पण तो आज झाला नाही स्वामींच्या",
    "start_time": 2192.0,
    "duration": 4.079
  },
  {
    "text": "स्मरणाचा झाला त्याच्या मागे आपल्याला",
    "start_time": 2194.24,
    "duration": 3.44
  },
  {
    "text": "माहितच आहे बिडकर महाराजांचा झाला",
    "start_time": 2196.079,
    "duration": 4.0
  },
  {
    "text": "त्याच्या मागे तुकोबांचा झाला सगळेच",
    "start_time": 2197.68,
    "duration": 4.56
  },
  {
    "text": "एकमेकांना जोडले गेलेले आहेत त्यांनाही",
    "start_time": 2200.079,
    "duration": 5.201
  },
  {
    "text": "एकमेकांचे कौतुक होतं स्मरण होतं त्याचा",
    "start_time": 2202.24,
    "duration": 6.48
  },
  {
    "text": "आनंद होतो एवढ नक्की तेव्हा हा जो",
    "start_time": 2205.28,
    "duration": 6.0
  },
  {
    "text": "संन्यासी बसला होता तपश्चला",
    "start_time": 2208.72,
    "duration": 6.16
  },
  {
    "text": "काही झालं तरी दत्त दर्शन पाहिजे म्हणून",
    "start_time": 2211.28,
    "duration": 6.0
  },
  {
    "text": "शेवटी तो एका क्षण असा येतो आणि असा",
    "start_time": 2214.88,
    "duration": 5.199
  },
  {
    "text": "साधनेमध्ये क्षण येतो आपले संन्यासा नाही",
    "start_time": 2217.28,
    "duration": 4.799
  },
  {
    "text": "सगळ पुन्हा कुठे निगडीत तेवढ सांगून",
    "start_time": 2220.079,
    "duration": 3.681
  },
  {
    "text": "संपवतो",
    "start_time": 2222.079,
    "duration": 3.681
  },
  {
    "text": "असा एक क्षण येतो की आपण इतक करतो इतक",
    "start_time": 2223.76,
    "duration": 4.8
  },
  {
    "text": "करतोय पण आपल्याला ते काही लाभत नाही",
    "start_time": 2225.76,
    "duration": 5.599
  },
  {
    "text": "लाभायला हवं असं वाटत आता लाभायला हवं असं",
    "start_time": 2228.56,
    "duration": 4.72
  },
  {
    "text": "वाटतं ते सुद्धा आपलंच असत सगळं मनाच बर",
    "start_time": 2231.359,
    "duration": 4.321
  },
  {
    "text": "का त्यांना काय द्यायचं याचा कोणी विचारच",
    "start_time": 2233.28,
    "duration": 4.48
  },
  {
    "text": "करत नाही मला काय मिळायला पाहिजे ते आपण",
    "start_time": 2235.68,
    "duration": 4.399
  },
  {
    "text": "ठरवलेल असत आपण करत रागायच तर भक्तीमध्ये",
    "start_time": 2237.76,
    "duration": 5.12
  },
  {
    "text": "काही ठरवू नये हे खरं उत्तर आहे त्याच",
    "start_time": 2240.079,
    "duration": 5.04
  },
  {
    "text": "भक्तीमध्ये काही ठरू नये तरी सुद्धा जर",
    "start_time": 2242.88,
    "duration": 4.64
  },
  {
    "text": "काही असं झालंच तर ते आपलं सर्वसाधारण असं",
    "start_time": 2245.119,
    "duration": 4.48
  },
  {
    "text": "होत असत हे त्यावर लक्षात आलं तेव्हा",
    "start_time": 2247.52,
    "duration": 5.92
  },
  {
    "text": "त्याला ते पाहिजे तर त्यानी काय उद्गार",
    "start_time": 2249.599,
    "duration": 5.76
  },
  {
    "text": "काढायला सुरुवात केली त्या दिवशी की संपली",
    "start_time": 2253.44,
    "duration": 5.12
  },
  {
    "text": "त्याचा पेशन्स संपला साध्या भाषेमध्ये",
    "start_time": 2255.359,
    "duration": 7.681
  },
  {
    "text": "की हा मला गुरुमंत्र एवढा मिळाला तो इतका",
    "start_time": 2258.56,
    "duration": 9.36
  },
  {
    "text": "तीव्रतेने इतका काळ मी सगळं सोसून या",
    "start_time": 2263.04,
    "duration": 7.6
  },
  {
    "text": "गरठ्याच थंडी वाऱ्याच सगळ्या सोसून मी हा",
    "start_time": 2267.92,
    "duration": 7.76
  },
  {
    "text": "करतोय तर मला ते जर इतके क्लेश सोसून फळ",
    "start_time": 2270.64,
    "duration": 8.56
  },
  {
    "text": "मिळत नसेल तर काय उपयोग झाला आणि हे जे",
    "start_time": 2275.68,
    "duration": 7.679
  },
  {
    "text": "सगळ्या कथा सांगतात त्या ज्या मिळकणी",
    "start_time": 2279.2,
    "duration": 8.72
  },
  {
    "text": "मुक्त झाला झाल सगळ खोट आहे अ त्याची सुरू",
    "start_time": 2283.359,
    "duration": 8.081
  },
  {
    "text": "झाल मनामध्ये प्रचंड",
    "start_time": 2287.92,
    "duration": 5.36
  },
  {
    "text": "म्हल आता हे संपल आपल्या दृष्टीने आता",
    "start_time": 2291.44,
    "duration": 4.639
  },
  {
    "text": "्याच्यावर कशावर विश्वास न ठेवताच्या पुढे",
    "start_time": 2293.28,
    "duration": 5.92
  },
  {
    "text": "आपण जाऊ इथपर्यंत",
    "start_time": 2296.079,
    "duration": 5.921
  },
  {
    "text": "त्या रात्री झोपला त्याला तिथेच जवळच्या",
    "start_time": 2299.2,
    "duration": 5.919
  },
  {
    "text": "डोंगरावर त्याला एक गुहा दिसली तू त्या",
    "start_time": 2302.0,
    "duration": 6.8
  },
  {
    "text": "गुहेत जा एवढ कळल ऐकू आल बाकी काही कळलं",
    "start_time": 2305.119,
    "duration": 8.24
  },
  {
    "text": "नाही दुसऱ्या दिवशी डोंगराची वाट धरली आता",
    "start_time": 2308.8,
    "duration": 7.12
  },
  {
    "text": "एक शेवटचा प्रयत्न आहे आता तर या तथ्याने",
    "start_time": 2313.359,
    "duration": 4.801
  },
  {
    "text": "हे कळलेलच आहे तरी सुद्धा एवढं जर स्वप्न",
    "start_time": 2315.92,
    "duration": 4.0
  },
  {
    "text": "झाले तर आपल्या मनाच काय आहे का नाही एवढी",
    "start_time": 2318.16,
    "duration": 4.88
  },
  {
    "text": "तरी खात्री करू म्हणून गेले होते ते गेले",
    "start_time": 2319.92,
    "duration": 6.48
  },
  {
    "text": "गुहा सापडली स्वप्नात दिसल्याप्रमाणे होती",
    "start_time": 2323.04,
    "duration": 6.24
  },
  {
    "text": "आत गेल्यावर समोर दिसले तिथे स्वामी",
    "start_time": 2326.4,
    "duration": 5.88
  },
  {
    "text": "बसलेले",
    "start_time": 2329.28,
    "duration": 3.0
  },
  {
    "text": "तेव्हा त्या ठिकाणी गुहेत गेल्यावर",
    "start_time": 2332.56,
    "duration": 6.88
  },
  {
    "text": "अक्कलकोट स्वामी महाराज बसले होते कसे आले",
    "start_time": 2335.839,
    "duration": 6.401
  },
  {
    "text": "होते ते त्याला जे दत्त दर्शन हव होत ते",
    "start_time": 2339.44,
    "duration": 4.88
  },
  {
    "text": "कोणत्या स्वरूपात मिळणार होतं याची एक",
    "start_time": 2342.24,
    "duration": 5.44
  },
  {
    "text": "योजना असते तेव्हा ते",
    "start_time": 2344.32,
    "duration": 5.84
  },
  {
    "text": "त्यांना पाहिल्याबरोबर त्याला वाटल इथ",
    "start_time": 2347.68,
    "duration": 5.52
  },
  {
    "text": "स्वामी बसलेले दिसतात आपल्याला स्वप्न पडल",
    "start_time": 2350.16,
    "duration": 5.36
  },
  {
    "text": "इथपर्यंत सगळं बरोबर आहे गुहा पण बरोबर",
    "start_time": 2353.2,
    "duration": 5.04
  },
  {
    "text": "आहे आपल्याला दाखवलेला मार्ग पण बरोबर",
    "start_time": 2355.52,
    "duration": 4.96
  },
  {
    "text": "काहीतरी होणार ्याच्यात हे होणार होत ते",
    "start_time": 2358.24,
    "duration": 5.119
  },
  {
    "text": "पण झालेल आहे पण बसलेले पुरुष महापुरुष",
    "start_time": 2360.48,
    "duration": 5.28
  },
  {
    "text": "दिसतात कोणीतरी सत्पुरुष दिसतात एवढ खरं",
    "start_time": 2363.359,
    "duration": 6.321
  },
  {
    "text": "पण आपल्याला दत्त दर्शन ते नाही म्हणून",
    "start_time": 2365.76,
    "duration": 5.44
  },
  {
    "text": "त्यानी क्षणात पुन्हा बघितल तेव्हा",
    "start_time": 2369.68,
    "duration": 4.08
  },
  {
    "text": "त्याच्या समोर दत्त",
    "start_time": 2371.2,
    "duration": 5.68
  },
  {
    "text": "समोर जसे त्याच्या त्याला जस तीन सहा हात",
    "start_time": 2373.76,
    "duration": 6.0
  },
  {
    "text": "तसे माझा दंड होत तसं तसं समोर दत्त",
    "start_time": 2376.88,
    "duration": 5.52
  },
  {
    "text": "स्वरूप होत त्याच्या सहन झालेले डोळे",
    "start_time": 2379.76,
    "duration": 6.24
  },
  {
    "text": "मिटले पायावर डोक ठेवलं स्वामी महाराज परत",
    "start_time": 2382.4,
    "duration": 5.6
  },
  {
    "text": "होते तसेच",
    "start_time": 2386.0,
    "duration": 4.32
  },
  {
    "text": "ते म्हणाले",
    "start_time": 2388.0,
    "duration": 5.119
  },
  {
    "text": "त्यालाही ते आवरेना की ठीक आहे इतक जे",
    "start_time": 2390.32,
    "duration": 6.08
  },
  {
    "text": "केलं आपण सोसलं तर त्याचं काहीतरी फळ",
    "start_time": 2393.119,
    "duration": 5.761
  },
  {
    "text": "आपल्या शेवटी मिळायला हव वाटत होत ते",
    "start_time": 2396.4,
    "duration": 4.24
  },
  {
    "text": "मिळाला",
    "start_time": 2398.88,
    "duration": 6.0
  },
  {
    "text": "सार्थक झाला काल मी खंत केली शेवटची असेल",
    "start_time": 2400.64,
    "duration": 7.199
  },
  {
    "text": "ती चुकली असेल पण तिच शेवट फळ चांगल आल",
    "start_time": 2404.88,
    "duration": 5.52
  },
  {
    "text": "असं म्हणून त्यांनी स्वामींच्या पाया पडून",
    "start_time": 2407.839,
    "duration": 4.561
  },
  {
    "text": "सांगितल की माझ्या आयुष्याच सार्थक झाल",
    "start_time": 2410.4,
    "duration": 5.28
  },
  {
    "text": "फक्त एवढीच इच्छा आहे मला तुमच्या पायाशी",
    "start_time": 2412.4,
    "duration": 5.6
  },
  {
    "text": "कायमचा ठेवा",
    "start_time": 2415.68,
    "duration": 4.88
  },
  {
    "text": "एवढी इच्छा आहे",
    "start_time": 2418.0,
    "duration": 6.48
  },
  {
    "text": "सेवा द्या जन्मोजन्मी मला सेवा द्या",
    "start_time": 2420.56,
    "duration": 8.48
  },
  {
    "text": "तेव्हा त्यावर स्वामी महाराज काय म्हणाले",
    "start_time": 2424.48,
    "duration": 6.32
  },
  {
    "text": "की",
    "start_time": 2429.04,
    "duration": 4.24
  },
  {
    "text": "आता म्हणले तुम्ही जा तुमचं काम झालेल आहे",
    "start_time": 2430.8,
    "duration": 5.6
  },
  {
    "text": "तुम्हाला कायमची सेवा पाहिजे ना त आता",
    "start_time": 2433.28,
    "duration": 7.76
  },
  {
    "text": "आमची नामस्मरण रूपी सेवा कायम करा",
    "start_time": 2436.4,
    "duration": 7.84
  },
  {
    "text": "तीच तुम्हाला पुढे उद्ध धरून जाईल",
    "start_time": 2441.04,
    "duration": 5.52
  },
  {
    "text": "तेव्हा त्यानी शेवटचे आपल्याला सेवा काय",
    "start_time": 2444.24,
    "duration": 5.52
  },
  {
    "text": "सांगितली ती लक्षात असावी",
    "start_time": 2446.56,
    "duration": 6.0
  },
  {
    "text": "त्यासाठी तिथे सुद्धा पुन्हा खुणा काय",
    "start_time": 2449.76,
    "duration": 5.12
  },
  {
    "text": "असतात आणि त्या एकमेकांशी कशा जोडलेल्या",
    "start_time": 2452.56,
    "duration": 5.039
  },
  {
    "text": "असतात तेव्हा आमची आता नामस्मरण रूपी सेवा",
    "start_time": 2454.88,
    "duration": 5.04
  },
  {
    "text": "करावी",
    "start_time": 2457.599,
    "duration": 4.881
  },
  {
    "text": "त्यानच तुम्हाला हे सगळं लाभेल पुढचं जे",
    "start_time": 2459.92,
    "duration": 5.04
  },
  {
    "text": "तुम्हाला हव आहे ते जे हवं होतं आता ते",
    "start_time": 2462.48,
    "duration": 5.359
  },
  {
    "text": "मिळालेल आहे.",
    "start_time": 2464.96,
    "duration": 5.84
  },
  {
    "text": "त्यांना त्यांनी आयुष्यभर नामस्मरण रूपी",
    "start_time": 2467.839,
    "duration": 5.121
  },
  {
    "text": "सेवा करायला सांगितली. आज आपण स्वामींच",
    "start_time": 2470.8,
    "duration": 5.279
  },
  {
    "text": "स्मरण करतो आहोत. हे त्यांचे शब्द आहेत ते",
    "start_time": 2472.96,
    "duration": 6.72
  },
  {
    "text": "संन्यासासाठी आहेत त्याला ठीक आहे एक वेळ",
    "start_time": 2476.079,
    "duration": 6.161
  },
  {
    "text": "त्याच्या मागे त्यांनी सगळं सोडूनच दिले",
    "start_time": 2479.68,
    "duration": 5.52
  },
  {
    "text": "पण त्याच्या माग आपल्यासारखे प्रपंचाचे",
    "start_time": 2482.24,
    "duration": 6.879
  },
  {
    "text": "पाश किंवा काच नाहीयेत किंवा काम",
    "start_time": 2485.2,
    "duration": 6.56
  },
  {
    "text": "कर्तव्य ही सगळी नाहीयेत आज आपण सगळ्या",
    "start_time": 2489.119,
    "duration": 5.521
  },
  {
    "text": "वयाची माणस इथे बसलेले आहोत",
    "start_time": 2491.76,
    "duration": 6.72
  },
  {
    "text": "यातलं एक नक्की आहे की प्रत्येकाला",
    "start_time": 2494.64,
    "duration": 6.24
  },
  {
    "text": "काहीतरी वेळ मिळणारच",
    "start_time": 2498.48,
    "duration": 4.879
  },
  {
    "text": "तो त्यांनी नामासाठी वापरला तरी त्यांची",
    "start_time": 2500.88,
    "duration": 4.719
  },
  {
    "text": "नामस्म स्मरण रूपी सेवा आपल्याला त्यांनी",
    "start_time": 2503.359,
    "duration": 4.561
  },
  {
    "text": "संन्यासा सारखी केली असेल आपण आपल्या",
    "start_time": 2505.599,
    "duration": 5.201
  },
  {
    "text": "ठेवणीप्रमाणे करू ती आपण करत राहू जे",
    "start_time": 2507.92,
    "duration": 5.679
  },
  {
    "text": "आपल्याला नाम मिळाला असेल मिळाल नसेल तर",
    "start_time": 2510.8,
    "duration": 6.0
  },
  {
    "text": "जे आपण घेत असाल त्या नामाची सेवा करा",
    "start_time": 2513.599,
    "duration": 6.0
  },
  {
    "text": "स्वामींना पुरेल आणि त्याचा उद्धार मी",
    "start_time": 2516.8,
    "duration": 5.36
  },
  {
    "text": "करीन त्यांनी शेवटी जे तला टेकून शेवटी",
    "start_time": 2519.599,
    "duration": 8.72
  },
  {
    "text": "सांगितलं अनन्या चिंतन ते योजना",
    "start_time": 2522.16,
    "duration": 10.0
  },
  {
    "text": "अनन्य भावाने आपण आपपल्या श्रद्धा स्थानाच",
    "start_time": 2528.319,
    "duration": 6.161
  },
  {
    "text": "स्मरण करीत राहू",
    "start_time": 2532.16,
    "duration": 5.36
  },
  {
    "text": "तर योगक्ष",
    "start_time": 2534.48,
    "duration": 7.2
  },
  {
    "text": "म्हणून स्वामी आहे योगक्ष वाहतील तसा ते",
    "start_time": 2537.52,
    "duration": 7.52
  },
  {
    "text": "आपलाही वाहतील फक्त आपल्याला जे शक्य आहे",
    "start_time": 2541.68,
    "duration": 7.919
  },
  {
    "text": "जिथे जसे आहोत तस जे आवडत ते पण देवाच नाम",
    "start_time": 2545.04,
    "duration": 7.92
  },
  {
    "text": "आपण उतरून आणि त्यानी आपल्याला उतरून ्याव",
    "start_time": 2549.599,
    "duration": 6.48
  },
  {
    "text": "स्वामींच्या चरणी प्रार्थना",
    "start_time": 2552.96,
    "duration": 5.04
  },
  {
    "text": "325",
    "start_time": 2556.079,
    "duration": 7.04
  },
  {
    "text": "स्वामी देई हेची दान",
    "start_time": 2558.0,
    "duration": 6.72
  },
  {
    "text": "स्वामी",
    "start_time": 2563.119,
    "duration": 8.801
  },
  {
    "text": "देई हेची दान नित्य चरणांचे दर्शन नित्य",
    "start_time": 2564.72,
    "duration": 12.879
  },
  {
    "text": "चरणांचे दर्शन स्वामी देई हे",
    "start_time": 2571.92,
    "duration": 10.24
  },
  {
    "text": "स्वामी देई हे",
    "start_time": 2577.599,
    "duration": 8.081
  },
  {
    "text": "मज नको धनारा",
    "start_time": 2582.16,
    "duration": 10.32
  },
  {
    "text": "तुझ्या चरणी द्यावा तारा मजन नको धनारा",
    "start_time": 2585.68,
    "duration": 11.36
  },
  {
    "text": "तुझ्या चरणी द्यावा थारा तुझ्या चरणी",
    "start_time": 2592.48,
    "duration": 11.52
  },
  {
    "text": "द्यावा थारा देई हेची दान नित्य चरणांचे",
    "start_time": 2597.04,
    "duration": 13.84
  },
  {
    "text": "दर्शन नित्य चरणांचे दर्शन स्वामी देई हेच",
    "start_time": 2604.0,
    "duration": 12.0
  },
  {
    "text": "दान स्वामी देई हेच दान हे जे आपण अभंग",
    "start_time": 2610.88,
    "duration": 8.719
  },
  {
    "text": "म्हणतो यामध्ये क्रम आहे स्वामींच्या",
    "start_time": 2616.0,
    "duration": 5.2
  },
  {
    "text": "स्वामी सुतांचा ज्यांचा सुरुवातीला ला",
    "start_time": 2619.599,
    "duration": 4.24
  },
  {
    "text": "उल्लेख केला त्यांचच हे आहे त्यांनी हे",
    "start_time": 2621.2,
    "duration": 4.48
  },
  {
    "text": "सगळं नको म्हटलं त्यांच्या मागे सुद्धा",
    "start_time": 2623.839,
    "duration": 6.321
  },
  {
    "text": "प्रपंच होता हे सगळं आहे पण हे माझी त्याग",
    "start_time": 2625.68,
    "duration": 8.159
  },
  {
    "text": "करण्याची तयारी आहे मग काय मागितल ते हव",
    "start_time": 2630.16,
    "duration": 8.24
  },
  {
    "text": "आहे तुझे नामी लागो छंद मज द्यावे दास भरत",
    "start_time": 2633.839,
    "duration": 8.721
  },
  {
    "text": "भगवंताच खर दास्यत्व लागो हे मागितलेल आहे",
    "start_time": 2638.4,
    "duration": 7.199
  },
  {
    "text": "आणि मागितलेल आहे ते नामाचा छंद लागो अस",
    "start_time": 2642.56,
    "duration": 6.0
  },
  {
    "text": "मागितले आहे प्रपंच नाही सुटला पण छंद",
    "start_time": 2645.599,
    "duration": 7.601
  },
  {
    "text": "नामाचा लागला आपल्या प्रपंचाचा छंद",
    "start_time": 2648.56,
    "duration": 6.799
  },
  {
    "text": "बारीक असत हे वाटत आपल्याला आपल्याला",
    "start_time": 2653.2,
    "duration": 4.159
  },
  {
    "text": "म्हणताना सुद्धा मझ ठेवावे भिकारी असं कसं",
    "start_time": 2655.359,
    "duration": 4.801
  },
  {
    "text": "सांगायचं आपण तर सगळे एवढ सगळ गोळा",
    "start_time": 2657.359,
    "duration": 5.841
  },
  {
    "text": "करायसाठी बसलेली माणस माझ ठेवावे भिकारी",
    "start_time": 2660.16,
    "duration": 6.72
  },
  {
    "text": "म्हल्यानंतर असं समजा ठेवलंच",
    "start_time": 2663.2,
    "duration": 5.84
  },
  {
    "text": "स्वामी शेवटी काय सगळे रात्रीत काढून",
    "start_time": 2666.88,
    "duration": 4.479
  },
  {
    "text": "घेतील काय सांगताय ते शेअरचे भाव कसळून",
    "start_time": 2669.04,
    "duration": 4.64
  },
  {
    "text": "माणसं भिकारी होत नाहीत",
    "start_time": 2671.359,
    "duration": 5.121
  },
  {
    "text": "कंपन्या एका रात्रीत पडत नाहीत होतं सगळं",
    "start_time": 2673.68,
    "duration": 4.399
  },
  {
    "text": "असलं काहीतरी स्वामीन मागितलं आणि",
    "start_time": 2676.48,
    "duration": 4.48
  },
  {
    "text": "मनापासून मागितल आपण आता इतक्या भावान",
    "start_time": 2678.079,
    "duration": 6.801
  },
  {
    "text": "वा म्हणणार छान भेटलाय का असा कोणी",
    "start_time": 2680.96,
    "duration": 6.56
  },
  {
    "text": "मागणारा भेटतच नाही मला हेच द्यायच म्हणले",
    "start_time": 2684.88,
    "duration": 6.64
  },
  {
    "text": "समजा काय करायच अस भीती वाटते ना तशी भीती",
    "start_time": 2687.52,
    "duration": 7.0
  },
  {
    "text": "वाटून",
    "start_time": 2691.52,
    "duration": 3.0
  },
  {
    "text": "ठेवा बघू सुखे करीन चाकरी",
    "start_time": 2694.72,
    "duration": 6.879
  },
  {
    "text": "ही लौकिक चाकरी आहे त पोट भरती तर त्यांची",
    "start_time": 2698.88,
    "duration": 5.68
  },
  {
    "text": "चाकरी केली तर काय भरेल याची कल्पना म्हणू",
    "start_time": 2701.599,
    "duration": 5.961
  },
  {
    "text": "शक",
    "start_time": 2704.56,
    "duration": 3.0
  },
  {
    "text": "समजा कल्पना करा लौकिकातल अन्न आहे ते चार",
    "start_time": 2707.92,
    "duration": 5.439
  },
  {
    "text": "घास खाल्ले तर माणसाला पाचवा घास नको",
    "start_time": 2711.52,
    "duration": 3.92
  },
  {
    "text": "म्हणतो मनुष्य",
    "start_time": 2713.359,
    "duration": 4.401
  },
  {
    "text": "्याला घासच न घालता पोट भरला असेल तर काय",
    "start_time": 2715.44,
    "duration": 4.8
  },
  {
    "text": "पाहिजे आपल्याला हा भाव आहे त्याच्यामध्ये",
    "start_time": 2717.76,
    "duration": 7.28
  },
  {
    "text": "लक्षात घेऊन मज नको धनदारा",
    "start_time": 2720.24,
    "duration": 11.44
  },
  {
    "text": "आसक्ती नको म्हणायच नाही मज नको धन दारा",
    "start_time": 2725.04,
    "duration": 13.2
  },
  {
    "text": "तुझ्या चरणी जावा थारा मज नको धनारा",
    "start_time": 2731.68,
    "duration": 11.04
  },
  {
    "text": "तुझ्या चरणी द्यावा थारा तुझ्या चरणी",
    "start_time": 2738.24,
    "duration": 11.119
  },
  {
    "text": "द्यावा थारा देई हेची दान नित्य चरणांचे",
    "start_time": 2742.72,
    "duration": 12.48
  },
  {
    "text": "दर्शन नित्य चरणांचे दर्शन स्वामी देई",
    "start_time": 2749.359,
    "duration": 11.76
  },
  {
    "text": "हेची दान स्वामी देई हेची दान",
    "start_time": 2755.2,
    "duration": 12.399
  },
  {
    "text": "मज ठेवावे भिकारी सुखे करीन चाकरी",
    "start_time": 2761.119,
    "duration": 8.641
  },
  {
    "text": "मज ठेवा",
    "start_time": 2767.599,
    "duration": 6.401
  },
  {
    "text": "नाही सुखे करीन चाकरी",
    "start_time": 2769.76,
    "duration": 7.52
  },
  {
    "text": "सुखे करीन चाकरी",
    "start_time": 2774.0,
    "duration": 9.76
  },
  {
    "text": "देई हेची दान नित्य चरणांच दर्शन नित्य",
    "start_time": 2777.28,
    "duration": 13.039
  },
  {
    "text": "चरणांचे दर्शन स्वामी देई हेचि नाम स्वामी",
    "start_time": 2783.76,
    "duration": 9.839
  },
  {
    "text": "देई हेचि नाम",
    "start_time": 2790.319,
    "duration": 9.76
  },
  {
    "text": "तुझे नाम माझी जोड मुखी राहते तेची गोड",
    "start_time": 2793.599,
    "duration": 12.801
  },
  {
    "text": "तुझे नाम माझी गोड मुखी राहो तेची गोड",
    "start_time": 2800.079,
    "duration": 12.961
  },
  {
    "text": "मुखी राहो तेची गोड देई हेची दान नित्य",
    "start_time": 2806.4,
    "duration": 13.04
  },
  {
    "text": "चरणांचे दर्शन नित्य चरणांचे दर्शन स्वामी",
    "start_time": 2813.04,
    "duration": 12.88
  },
  {
    "text": "देई हेचि दान स्वामी देई हेची धामी",
    "start_time": 2819.44,
    "duration": 10.8
  },
  {
    "text": "तुझ्या चरणी माझा माझा माथा ऐसे करी",
    "start_time": 2825.92,
    "duration": 10.08
  },
  {
    "text": "दिलाना नाथा तुझ्या चरणी माझा माथा ऐसे",
    "start_time": 2830.24,
    "duration": 8.4
  },
  {
    "text": "करी दिनाथा",
    "start_time": 2836.0,
    "duration": 5.839
  },
  {
    "text": "ऐसे करी दिनाथा",
    "start_time": 2838.64,
    "duration": 9.6
  },
  {
    "text": "देई हेचि दान नित्य चरणांचे दर्शन नित्य",
    "start_time": 2841.839,
    "duration": 12.801
  },
  {
    "text": "चरणांचे दर्शन स्वामी देई हेचि धान स्वामी",
    "start_time": 2848.24,
    "duration": 9.599
  },
  {
    "text": "देई हेचि धामी",
    "start_time": 2854.64,
    "duration": 9.84
  },
  {
    "text": "तुझे नामी लावो छंद मज द्यावे दास पर तुझे",
    "start_time": 2857.839,
    "duration": 13.921
  },
  {
    "text": "नामी लावो छंद मज द्यावे दास पर मज द्यावे",
    "start_time": 2864.48,
    "duration": 9.119
  },
  {
    "text": "दास",
    "start_time": 2871.76,
    "duration": 8.24
  },
  {
    "text": "देई हेची दान नित्य शरणामचे दर्शन नित्य",
    "start_time": 2873.599,
    "duration": 13.361
  },
  {
    "text": "शरणाम दर्शन स्वामी देई हेची स्वामी देई",
    "start_time": 2880.0,
    "duration": 9.44
  },
  {
    "text": "हेची दान",
    "start_time": 2886.96,
    "duration": 8.8
  },
  {
    "text": "सुत मागे हेची दान तुझ्या चरणी होईलीन",
    "start_time": 2889.44,
    "duration": 12.56
  },
  {
    "text": "सुख मागे हेची दान तुझ्या चरणी होईलन",
    "start_time": 2895.76,
    "duration": 9.359
  },
  {
    "text": "तुझ्या चरणी होईलीन",
    "start_time": 2902.0,
    "duration": 9.359
  },
  {
    "text": "देई हेची दान नित्य चरणांचे दर्शन नित्य",
    "start_time": 2905.119,
    "duration": 11.361
  },
  {
    "text": "चरणांचे दर्शन स्वामी देई हेची",
    "start_time": 2911.359,
    "duration": 13.0
  },
  {
    "text": "स्वामी देई हे स्वामी देई हे",
    "start_time": 2916.48,
    "duration": 7.879
  },
  {
    "text": "जानकी",
    "start_time": 2925.76,
    "duration": 6.599
  },
  {
    "text": "वनस्मरण जय जय राम ओम",
    "start_time": 2927.52,
    "duration": 4.839
  },
  {
    "text": "[संगीत]",
    "start_time": 2934.57,
    "duration": 3.059
  }
]